{
  "questions": [
    {
      "id": "cow_001",
      "question": "ഏറ്റവും വലിയ ഭൂഖണ്ഡം ഏതാണ്?",
      "options": [
        "ഏഷ്യ",
        "ആഫ്രിക്ക",
        "ഉത്തര അമേരിക്ക",
        "യൂറോപ്പ്"
      ],
      "answer": "ഏഷ്യ",
      "difficulty": "easy"
    },
    {
      "id": "cow_002",
      "question": "ലോകത്തിലെ ഏറ്റവും ചെറിയ ഭൂഖണ്ഡം ഏതാണ്?",
      "options": [
        "യൂറോപ്പ്",
        "ഓസ്‌ട്രേലിയ",
        "അന്റാർട്ടിക്ക",
        "തെക്കേ അമേരിക്ക"
      ],
      "answer": "ഓസ്‌ട്രേലിയ",
      "difficulty": "easy"
    },
    {
      "id": "cow_003",
      "question": "ഏറ്റവും കൂടുതൽ ജനസംഖ്യയുള്ള ഭൂഖണ്ഡം ഏതാണ്?",
      "options": [
        "ആഫ്രിക്ക",
        "യൂറോപ്പ്",
        "ഏഷ്യ",
        "ഉത്തര അമേരിക്ക"
      ],
      "answer": "ഏഷ്യ",
      "difficulty": "easy"
    },
    {
      "id": "cow_004",
      "question": "കറുത്ത ഭൂഖണ്ഡം (Dark Continent) എന്നറിയപ്പെടുന്നത് ഏതാണ്?",
      "options": [
        "ആഫ്രിക്ക",
        "അന്റാർട്ടിക്ക",
        "ഏഷ്യ",
        "ഓസ്‌ട്രേലിയ"
      ],
      "answer": "ആഫ്രിക്ക",
      "difficulty": "easy"
    },
    {
      "id": "cow_005",
      "question": "വെളുത്ത ഭൂഖണ്ഡം (White Continent) എന്നറിയപ്പെടുന്നത് ഏതാണ്?",
      "options": [
        "യൂറോപ്പ്",
        "ഉത്തര അമേരിക്ക",
        "അന്റാർട്ടിക്ക",
        "ഓസ്‌ട്രേലിയ"
      ],
      "answer": "അന്റാർട്ടിക്ക",
      "difficulty": "easy"
    },
    {
      "id": "cow_006",
      "question": "ഏറ്റവും കൂടുതൽ രാജ്യങ്ങളുള്ള ഭൂഖണ്ഡം ഏതാണ്?",
      "options": [
        "ഏഷ്യ",
        "ആഫ്രിക്ക",
        "യൂറോപ്പ്",
        "തെക്കേ അമേരിക്ക"
      ],
      "answer": "ആഫ്രിക്ക",
      "difficulty": "easy"
    },
    {
      "id": "cow_007",
      "question": "കംഗാരുക്കളുടെ നാട് എന്നറിയപ്പെടുന്ന ഭൂഖണ്ഡം ഏതാണ്?",
      "options": [
        "ഓസ്‌ട്രേലിയ",
        "ആഫ്രിക്ക",
        "അന്റാർട്ടിക്ക",
        "യൂറോപ്പ്"
      ],
      "answer": "ഓസ്‌ട്രേലിയ",
      "difficulty": "easy"
    },
    {
      "id": "cow_008",
      "question": "ലോകത്തിലെ ഏറ്റവും നീളം കൂടിയ നദിയായ നൈൽ ഒഴുകുന്ന ഭൂഖണ്ഡം ഏതാണ്?",
      "options": [
        "ഏഷ്യ",
        "തെക്കേ അമേരിക്ക",
        "ആഫ്രിക്ക",
        "ഉത്തര അമേരിക്ക"
      ],
      "answer": "ആഫ്രിക്ക",
      "difficulty": "easy"
    },
    {
      "id": "cow_009",
      "question": "ആമസോൺ മഴക്കാടുകൾ സ്ഥിതി ചെയ്യുന്നത് ഏത് ഭൂഖണ്ഡത്തിലാണ്?",
      "options": [
        "ഉത്തര അമേരിക്ക",
        "തെക്കേ അമേരിക്ക",
        "ആഫ്രിക്ക",
        "ഏഷ്യ"
      ],
      "answer": "തെക്കേ അമേരിക്ക",
      "difficulty": "easy"
    },
    {
      "id": "cow_010",
      "question": "ലോകത്തിലെ ഏറ്റവും ഉയർന്ന കൊടുമുടിയായ മൗണ്ട് എവറസ്റ്റ് ഏത് ഭൂഖണ്ഡത്തിലാണ്?",
      "options": [
        "യൂറോപ്പ്",
        "ഏഷ്യ",
        "ഉത്തര അമേരിക്ക",
        "ആഫ്രിക്ക"
      ],
      "answer": "ഏഷ്യ",
      "difficulty": "easy"
    },
    {
      "id": "cow_011",
      "question": "ഒരു മരുഭൂമി പോലും ഇല്ലാത്ത ഒരേയൊരു ഭൂഖണ്ഡം ഏതാണ്?",
      "options": [
        "യൂറോപ്പ്",
        "ഓസ്‌ട്രേലിയ",
        "ഉത്തര അമേരിക്ക",
        "തെക്കേ അമേരിക്ക"
      ],
      "answer": "യൂറോപ്പ്",
      "difficulty": "medium"
    },
    {
      "id": "cow_012",
      "question": "സ്ഥിരമായി മനുഷ്യവാസമില്ലാത്ത ഭൂഖണ്ഡം ഏതാണ്?",
      "options": [
        "ഓസ്‌ട്രേലിയ",
        "അന്റാർട്ടിക്ക",
        "ആഫ്രിക്ക",
        "യൂറോപ്പ്"
      ],
      "answer": "അന്റാർട്ടിക്ക",
      "difficulty": "easy"
    },
    {
      "id": "cow_013",
      "question": "വിസ്തീർണ്ണത്തിൽ രണ്ടാം സ്ഥാനത്തുള്ള ഭൂഖണ്ഡം ഏതാണ്?",
      "options": [
        "ആഫ്രിക്ക",
        "ഉത്തര അമേരിക്ക",
        "തെക്കേ അമേരിക്ക",
        "യൂറോപ്പ്"
      ],
      "answer": "ആഫ്രിക്ക",
      "difficulty": "easy"
    },
    {
      "id": "cow_014",
      "question": "ഭൂമധ്യരേഖ, കർക്കടക രേഖ, മകരരേഖ എന്നിവ കടന്നുപോകുന്ന ഒരേയൊരു ഭൂഖണ്ഡം ഏതാണ്?",
      "options": [
        "ഏഷ്യ",
        "ആഫ്രിക്ക",
        "തെക്കേ അമേരിക്ക",
        "ഓസ്‌ട്രേലിയ"
      ],
      "answer": "ആഫ്രിക്ക",
      "difficulty": "medium"
    },
    {
      "id": "cow_015",
      "question": "ലോകത്തിന്റെ ശ്വാസകോശം എന്നറിയപ്പെടുന്ന ആമസോൺ കാടുകൾ ഏത് ഭൂഖണ്ഡത്തിലാണ്?",
      "options": [
        "ആഫ്രിക്ക",
        "തെക്കേ അമേരിക്ക",
        "ഏഷ്യ",
        "ഓസ്‌ട്രേലിയ"
      ],
      "answer": "തെക്കേ അമേരിക്ക",
      "difficulty": "easy"
    },
    {
      "id": "cow_016",
      "question": "ഒരു ദ്വീപ് ഭൂഖണ്ഡം (Island Continent) എന്നറിയപ്പെടുന്നത് ഏതാണ്?",
      "options": [
        "അന്റാർട്ടിക്ക",
        "ഓസ്‌ട്രേലിയ",
        "യൂറോപ്പ്",
        "തെക്കേ അമേരിക്ക"
      ],
      "answer": "ഓസ്‌ട്രേലിയ",
      "difficulty": "easy"
    },
    {
      "id": "cow_017",
      "question": "ലോകത്തിലെ ഏറ്റവും വലിയ മരുഭൂമിയായ സഹാറ സ്ഥിതി ചെയ്യുന്നത് എവിടെയാണ്?",
      "options": [
        "ഏഷ്യ",
        "ഓസ്‌ട്രേലിയ",
        "ആഫ്രിക്ക",
        "തെക്കേ അമേരിക്ക"
      ],
      "answer": "ആഫ്രിക്ക",
      "difficulty": "easy"
    },
    {
      "id": "cow_018",
      "question": "യൂറോപ്പിനെയും ഏഷ്യയെയും വേർതിരിക്കുന്ന പർവതനിര ഏതാണ്?",
      "options": [
        "ആൽപ്സ്",
        "ഹിമാലയം",
        "ആൻഡീസ്",
        "യുറാൽ പർവതനിരകൾ"
      ],
      "answer": "യുറാൽ പർവതനിരകൾ",
      "difficulty": "medium"
    },
    {
      "id": "cow_019",
      "question": "ഏറ്റവും നീളം കൂടിയ പർവതനിരയായ ആൻഡീസ് സ്ഥിതി ചെയ്യുന്നത് ഏത് ഭൂഖണ്ഡത്തിലാണ്?",
      "options": [
        "ഉത്തര അമേരിക്ക",
        "തെക്കേ അമേരിക്ക",
        "ഏഷ്യ",
        "ആഫ്രിക്ക"
      ],
      "answer": "തെക്കേ അമേരിക്ക",
      "difficulty": "medium"
    },
    {
      "id": "cow_020",
      "question": "ലോകത്തിലെ ഏറ്റവും വലിയ ശുദ്ധജല തടാകമായ സുപ്പീരിയർ തടാകം ഏത് ഭൂഖണ്ഡത്തിലാണ്?",
      "options": [
        "യൂറോപ്പ്",
        "ഏഷ്യ",
        "ഉത്തര അമേരിക്ക",
        "ആഫ്രിക്ക"
      ],
      "answer": "ഉത്തര അമേരിക്ക",
      "difficulty": "medium"
    },
    {
      "id": "cow_021",
      "question": "അന്റാർട്ടിക്കയിലെ ഇന്ത്യയുടെ ആദ്യത്തെ ഗവേഷണ കേന്ദ്രം ഏതാണ്?",
      "options": [
        "ഭാരതി",
        "മൈത്രി",
        "ദക്ഷിണ ഗംഗോത്രി",
        "ഹിമാദ്രി"
      ],
      "answer": "ദക്ഷിണ ഗംഗോത്രി",
      "difficulty": "medium"
    },
    {
      "id": "cow_022",
      "question": "യൂറോപ്പിലെ ഏറ്റവും നീളം കൂടിയ നദി ഏതാണ്?",
      "options": [
        "ഡാന്യൂബ്",
        "വോൾഗ",
        "റൈൻ",
        "തേംസ്"
      ],
      "answer": "വോൾഗ",
      "difficulty": "medium"
    },
    {
      "id": "cow_023",
      "question": "പക്ഷികളുടെ ഭൂഖണ്ഡം (Continent of Birds) എന്നറിയപ്പെടുന്നത് ഏതാണ്?",
      "options": [
        "ആഫ്രിക്ക",
        "ഓസ്‌ട്രേലിയ",
        "തെക്കേ അമേരിക്ക",
        "ഏഷ്യ"
      ],
      "answer": "തെക്കേ അമേരിക്ക",
      "difficulty": "medium"
    },
    {
      "id": "cow_024",
      "question": "ലോകത്തിലെ ഏറ്റവും ഉയരം കൂടിയ വെള്ളച്ചാട്ടമായ എയ്ഞ്ചൽ വെള്ളച്ചാട്ടം ഏത് ഭൂഖണ്ഡത്തിലാണ്?",
      "options": [
        "ഉത്തര അമേരിക്ക",
        "ആഫ്രിക്ക",
        "തെക്കേ അമേരിക്ക",
        "ഏഷ്യ"
      ],
      "answer": "തെക്കേ അമേരിക്ക",
      "difficulty": "medium"
    },
    {
      "id": "cow_025",
      "question": "വിസ്തീർണ്ണത്തിൽ മൂന്നാം സ്ഥാനത്തുള്ള ഭൂഖണ്ഡം ഏതാണ്?",
      "options": [
        "യൂറോപ്പ്",
        "ഉത്തര അമേരിക്ക",
        "തെക്കേ അമേരിക്ക",
        "അന്റാർട്ടിക്ക"
      ],
      "answer": "ഉത്തര അമേരിക്ക",
      "difficulty": "medium"
    },
    {
      "id": "cow_026",
      "question": "ലോകത്തിലെ ഏറ്റവും ആഴം കൂടിയ തടാകമായ ബൈക്കൽ തടാകം ഏത് ഭൂഖണ്ഡത്തിലാണ്?",
      "options": [
        "യൂറോപ്പ്",
        "ഏഷ്യ",
        "ഉത്തര അമേരിക്ക",
        "ആഫ്രിക്ക"
      ],
      "answer": "ഏഷ്യ",
      "difficulty": "medium"
    },
    {
      "id": "cow_027",
      "question": "ഗ്രീൻലാൻഡ് ഭൂമിശാസ്ത്രപരമായി ഏത് ഭൂഖണ്ഡത്തിന്റെ ഭാഗമാണ്?",
      "options": [
        "യൂറോപ്പ്",
        "ഉത്തര അമേരിക്ക",
        "അന്റാർട്ടിക്ക",
        "ഏഷ്യ"
      ],
      "answer": "ഉത്തര അമേരിക്ക",
      "difficulty": "hard"
    },
    {
      "id": "cow_028",
      "question": "യൂറോപ്പും ഏഷ്യയും ചേർന്ന ഭൂപ്രദേശം പൊതുവായി അറിയപ്പെടുന്നത് എന്ത് പേരിൽ?",
      "options": [
        "യൂറേഷ്യ",
        "ഏഷ്യോപ്പ",
        "ആഫ്രോ-ഏഷ്യ",
        "യൂറോലാൻഡ്"
      ],
      "answer": "യൂറേഷ്യ",
      "difficulty": "easy"
    },
    {
      "id": "cow_029",
      "question": "ഉത്തര അമേരിക്കയെയും തെക്കേ അമേരിക്കയെയും തമ്മിൽ ബന്ധിപ്പിക്കുന്ന കരയിടുക്ക് ഏതാണ്?",
      "options": [
        "സൂയസ് കരയിടുക്ക്",
        "പനാമ കരയിടുക്ക്",
        "ജിബ്രാൾട്ടർ",
        "ബെറിംഗ് കരയിടുക്ക്"
      ],
      "answer": "പനാമ കരയിടുക്ക്",
      "difficulty": "medium"
    },
    {
      "id": "cow_030",
      "question": "ഏഷ്യയെയും ആഫ്രിക്കയെയും വേർതിരിക്കുന്ന കൃത്രിമ കനാൽ ഏതാണ്?",
      "options": [
        "പനാമ കനാൽ",
        "സൂയസ് കനാൽ",
        "കീൽ കനാൽ",
        "എറി കനാൽ"
      ],
      "answer": "സൂയസ് കനാൽ",
      "difficulty": "easy"
    },
    {
      "id": "cow_031",
      "question": "പെൻഗ്വിനുകളുടെ നാട് എന്നറിയപ്പെടുന്ന ഭൂഖണ്ഡം ഏതാണ്?",
      "options": [
        "ഓസ്‌ട്രേലിയ",
        "അന്റാർട്ടിക്ക",
        "യൂറോപ്പ്",
        "ഉത്തര അമേരിക്ക"
      ],
      "answer": "അന്റാർട്ടിക്ക",
      "difficulty": "easy"
    },
    {
      "id": "cow_032",
      "question": "ഏറ്റവും കൂടുതൽ സജീവ അഗ്നിപർവ്വതങ്ങളുള്ള 'റിംഗ് ഓഫ് ഫയർ' ഏത് സമുദ്രത്തോട് ചേർന്നാണ്, ഇത് ഏതെല്ലാം ഭൂഖണ്ഡങ്ങളെ സ്പർശിക്കുന്നു?",
      "options": [
        "അറ്റ്ലാന്റിക് (യൂറോപ്പ്, ആഫ്രിക്ക)",
        "പസഫിക് (ഏഷ്യ, അമേരിക്കൻ ഭൂഖണ്ഡങ്ങൾ)",
        "ഇന്ത്യൻ സമുദ്രം (ഏഷ്യ, ഓസ്ട്രേലിയ)",
        "ആർട്ടിക് സമുദ്രം"
      ],
      "answer": "പസഫിക് (ഏഷ്യ, അമേരിക്കൻ ഭൂഖണ്ഡങ്ങൾ)",
      "difficulty": "hard"
    },
    {
      "id": "cow_033",
      "question": "ഓസ്‌ട്രേലിയയിലെ ഏറ്റവും നീളം കൂടിയ നദി ഏതാണ്?",
      "options": [
        "ഡാർലിംഗ്",
        "മുറെ",
        "യാംഗ്ലി",
        "കോംഗോ"
      ],
      "answer": "മുറെ",
      "difficulty": "hard"
    },
    {
      "id": "cow_034",
      "question": "ലോകത്തിലെ ഏറ്റവും ഉയരം കൂടിയ പീഠഭൂമിയായ ടിബറ്റൻ പീഠഭൂമി ഏത് ഭൂഖണ്ഡത്തിലാണ്?",
      "options": [
        "യൂറോപ്പ്",
        "ആഫ്രിക്ക",
        "ഏഷ്യ",
        "ഉത്തര അമേരിക്ക"
      ],
      "answer": "ഏഷ്യ",
      "difficulty": "easy"
    },
    {
      "id": "cow_035",
      "question": "ഉത്തര അമേരിക്കയിലെ ഏറ്റവും ഉയർന്ന കൊടുമുടി ഏതാണ്?",
      "options": [
        "മൗണ്ട് വിൻസൺ",
        "മൗണ്ട് എൽബ്രസ്",
        "മൗണ്ട് ഡെനാലി (മക്കിൻലി)",
        "മൗണ്ട് കോസിയസ്കോ"
      ],
      "answer": "മൗണ്ട് ഡെനാലി (മക്കിൻലി)",
      "difficulty": "hard"
    },
    {
      "id": "cow_036",
      "question": "ആഫ്രിക്കയിലെ ഏറ്റവും ഉയർന്ന കൊടുമുടി ഏതാണ്?",
      "options": [
        "കിളിമഞ്ചാരോ",
        "കെനിയ",
        "എൽബ്രസ്",
        "അകോൻകാഗ്വ"
      ],
      "answer": "കിളിമഞ്ചാരോ",
      "difficulty": "medium"
    },
    {
      "id": "cow_037",
      "question": "തെക്കേ അമേരിക്കയിലെ ഏറ്റവും ഉയർന്ന കൊടുമുടി ഏതാണ്?",
      "options": [
        "അകോൻകാഗ്വ",
        "വിൻസൺ മാസിഫ്",
        "എവറസ്റ്റ്",
        "ഡെനാലി"
      ],
      "answer": "അകോൻകാഗ്വ",
      "difficulty": "hard"
    },
    {
      "id": "cow_038",
      "question": "യൂറോപ്പിലെ ഏറ്റവും ഉയർന്ന കൊടുമുടി ഏതാണ്?",
      "options": [
        "മോണ്ട് ബ്ലാങ്ക്",
        "മൗണ്ട് എൽബ്രസ്",
        "മാറ്റർഹോൺ",
        "ആൽപ്സ്"
      ],
      "answer": "മൗണ്ട് എൽബ്രസ്",
      "difficulty": "hard"
    },
    {
      "id": "cow_039",
      "question": "അന്റാർട്ടിക്കയിലെ ഏറ്റവും ഉയർന്ന കൊടുമുടി ഏതാണ്?",
      "options": [
        "വിൻസൺ മാസിഫ്",
        "എൽബ്രസ്",
        "കിളിമഞ്ചാരോ",
        "കോസിയസ്കോ"
      ],
      "answer": "വിൻസൺ മാസിഫ്",
      "difficulty": "hard"
    },
    {
      "id": "cow_040",
      "question": "ഓസ്‌ട്രേലിയയിലെ ഏറ്റവും ഉയർന്ന കൊടുമുടി ഏതാണ്?",
      "options": [
        "മൗണ്ട് കോസിയസ്കോ",
        "മൗണ്ട് കുക്ക്",
        "മൗണ്ട് വിൻസൺ",
        "മൗണ്ട് എവറസ്റ്റ്"
      ],
      "answer": "മൗണ്ട് കോസിയസ്കോ",
      "difficulty": "hard"
    },
    {
      "id": "cow_041",
      "question": "ലോകത്തിലെ ഏറ്റവും വലിയ ഉപ്പുപാടമായ 'സലാർ ഡി ഉയൂനി' ഏത് ഭൂഖണ്ഡത്തിലാണ്?",
      "options": [
        "ആഫ്രിക്ക",
        "തെക്കേ അമേരിക്ക",
        "ഏഷ്യ",
        "ഓസ്‌ട്രേലിയ"
      ],
      "answer": "തെക്കേ അമേരിക്ക",
      "difficulty": "hard"
    },
    {
      "id": "cow_042",
      "question": "ഏറ്റവും താഴ്ന്ന പ്രദേശമായ ചാവുകടൽ (Dead Sea) ഏത് ഭൂഖണ്ഡത്തിലാണ്?",
      "options": [
        "ആഫ്രിക്ക",
        "യൂറോപ്പ്",
        "ഏഷ്യ",
        "ഓസ്‌ട്രേലിയ"
      ],
      "answer": "ഏഷ്യ",
      "difficulty": "medium"
    },
    {
      "id": "cow_043",
      "question": "ലോകത്തിലെ ഏറ്റവും വരണ്ട മരുഭൂമിയായ അറ്റകാമ സ്ഥിതി ചെയ്യുന്നത് എവിടെയാണ്?",
      "options": [
        "ആഫ്രിക്ക",
        "ഓസ്‌ട്രേലിയ",
        "തെക്കേ അമേരിക്ക",
        "ഏഷ്യ"
      ],
      "answer": "തെക്കേ അമേരിക്ക",
      "difficulty": "medium"
    },
    {
      "id": "cow_044",
      "question": "ഗ്രേറ്റ് ബാരിയർ റീഫ് (Great Barrier Reef) ഏത് ഭൂഖണ്ഡത്തോട് ചേർന്നാണ് സ്ഥിതി ചെയ്യുന്നത്?",
      "options": [
        "ഏഷ്യ",
        "ഓസ്‌ട്രേലിയ",
        "ആഫ്രിക്ക",
        "ഉത്തര അമേരിക്ക"
      ],
      "answer": "ഓസ്‌ട്രേലിയ",
      "difficulty": "easy"
    },
    {
      "id": "cow_045",
      "question": "ഏത് ഭൂഖണ്ഡത്തെയാണ് 'ശാസ്ത്രത്തിനായി സമർപ്പിക്കപ്പെട്ട ഭൂഖണ്ഡം' എന്ന് വിളിക്കുന്നത്?",
      "options": [
        "യൂറോപ്പ്",
        "ആഫ്രിക്ക",
        "അന്റാർട്ടിക്ക",
        "ഓസ്‌ട്രേലിയ"
      ],
      "answer": "അന്റാർട്ടിക്ക",
      "difficulty": "medium"
    },
    {
      "id": "cow_046",
      "question": "വിക്ടോറിയ വെള്ളച്ചാട്ടം ഏത് ഭൂഖണ്ഡത്തിലാണ് സ്ഥിതി ചെയ്യുന്നത്?",
      "options": [
        "ആഫ്രിക്ക",
        "ഏഷ്യ",
        "തെക്കേ അമേരിക്ക",
        "ഉത്തര അമേരിക്ക"
      ],
      "answer": "ആഫ്രിക്ക",
      "difficulty": "medium"
    },
    {
      "id": "cow_047",
      "question": "നയാഗ്ര വെള്ളച്ചാട്ടം ഏത് ഭൂഖണ്ഡത്തിലാണ് സ്ഥിതി ചെയ്യുന്നത്?",
      "options": [
        "യൂറോപ്പ്",
        "ഉത്തര അമേരിക്ക",
        "തെക്കേ അമേരിക്ക",
        "ഏഷ്യ"
      ],
      "answer": "ഉത്തര അമേരിക്ക",
      "difficulty": "easy"
    },
    {
      "id": "cow_048",
      "question": "ലോകത്തിലെ ഏറ്റവും നീളമുള്ള കനാൽ ആയ ഗ്രാൻഡ് കനാൽ ഏത് ഭൂഖണ്ഡത്തിലാണ്?",
      "options": [
        "യൂറോപ്പ്",
        "ഏഷ്യ",
        "ഉത്തര അമേരിക്ക",
        "ആഫ്രിക്ക"
      ],
      "answer": "ഏഷ്യ",
      "difficulty": "hard"
    },
    {
      "id": "cow_049",
      "question": "പ്രാരൂപ് അഥവാ പുൽമേടുകളായ 'പ്രയറികൾ' (Prairies) കാണപ്പെടുന്നത് ഏത് ഭൂഖണ്ഡത്തിലാണ്?",
      "options": [
        "തെക്കേ അമേരിക്ക",
        "ഉത്തര അമേരിക്ക",
        "ആഫ്രിക്ക",
        "ഏഷ്യ"
      ],
      "answer": "ഉത്തര അമേരിക്ക",
      "difficulty": "medium"
    },
    {
      "id": "cow_050",
      "question": "'പമ്പാസ്' (Pampas) പുൽമേടുകൾ ഏത് ഭൂഖണ്ഡത്തിലാണ് ഉള്ളത്?",
      "options": [
        "ആഫ്രിക്ക",
        "ഓസ്‌ട്രേലിയ",
        "തെക്കേ അമേരിക്ക",
        "യൂറോപ്പ്"
      ],
      "answer": "തെക്കേ അമേരിക്ക",
      "difficulty": "medium"
    },
    {
      "id": "cow_051",
      "question": "ഏഷ്യയിലെ ഏറ്റവും നീളം കൂടിയ നദി ഏതാണ്?",
      "options": [
        "യാങ്‌സി (Yangtze)",
        "സിന്ധു",
        "ഗംഗ",
        "മേകോങ്"
      ],
      "answer": "യാങ്‌സി (Yangtze)",
      "difficulty": "medium"
    },
    {
      "id": "cow_052",
      "question": "ലോകത്തിലെ ഏറ്റവും വലിയ ഉൾനാടൻ കടലായ കാസ്പിയൻ കടൽ ഏതെല്ലാം ഭൂഖണ്ഡങ്ങൾക്ക് ഇടയിലാണ്?",
      "options": [
        "ആഫ്രിക്ക, യൂറോപ്പ്",
        "ഏഷ്യ, യൂറോപ്പ്",
        "ഉത്തര അമേരിക്ക, തെക്കേ അമേരിക്ക",
        "ഏഷ്യ, ആഫ്രിക്ക"
      ],
      "answer": "ഏഷ്യ, യൂറോപ്പ്",
      "difficulty": "hard"
    },
    {
      "id": "cow_053",
      "question": "വിസ്തീർണ്ണത്തിൽ നാലാം സ്ഥാനത്തുള്ള ഭൂഖണ്ഡം ഏതാണ്?",
      "options": [
        "അന്റാർട്ടിക്ക",
        "യൂറോപ്പ്",
        "തെക്കേ അമേരിക്ക",
        "ഓസ്‌ട്രേലിയ"
      ],
      "answer": "തെക്കേ അമേരിക്ക",
      "difficulty": "medium"
    },
    {
      "id": "cow_054",
      "question": "വിസ്തീർണ്ണത്തിൽ അഞ്ചാം സ്ഥാനത്തുള്ള ഭൂഖണ്ഡം ഏതാണ്?",
      "options": [
        "യൂറോപ്പ്",
        "അന്റാർട്ടിക്ക",
        "ഓസ്‌ട്രേലിയ",
        "തെക്കേ അമേരിക്ക"
      ],
      "answer": "അന്റാർട്ടിക്ക",
      "difficulty": "medium"
    },
    {
      "id": "cow_055",
      "question": "വിസ്തീർണ്ണത്തിൽ ആറാം സ്ഥാനത്തുള്ള ഭൂഖണ്ഡം ഏതാണ്?",
      "options": [
        "യൂറോപ്പ്",
        "അന്റാർട്ടിക്ക",
        "ഓസ്‌ട്രേലിയ",
        "ആഫ്രിക്ക"
      ],
      "answer": "യൂറോപ്പ്",
      "difficulty": "medium"
    },
    {
      "id": "cow_056",
      "question": "പ്രാദേശികമായി 'ഡൗൺ അണ്ടർ' (Down Under) എന്നറിയപ്പെടുന്ന ഭൂഖണ്ഡം ഏതാണ്?",
      "options": [
        "അന്റാർട്ടിക്ക",
        "ഓസ്‌ട്രേലിയ",
        "തെക്കേ അമേരിക്ക",
        "ആഫ്രിക്ക"
      ],
      "answer": "ഓസ്‌ട്രേലിയ",
      "difficulty": "easy"
    },
    {
      "id": "cow_057",
      "question": "ആഫ്രിക്കയിലെ ഏറ്റവും വലിയ തടാകം ഏതാണ്?",
      "options": [
        "ടാംഗനിക്ക തടാകം",
        "വിക്ടോറിയ തടാകം",
        "മാലവി തടാകം",
        "ചാഡ് തടാകം"
      ],
      "answer": "വിക്ടോറിയ തടാകം",
      "difficulty": "medium"
    },
    {
      "id": "cow_058",
      "question": "ഉത്തര അമേരിക്കയിലെ ഏറ്റവും നീളം കൂടിയ നദി ഏതാണ്?",
      "options": [
        "മിസിസിപ്പി-മിസൗറി",
        "ആമസോൺ",
        "കൊളറാഡോ",
        "യൂക്കോൺ"
      ],
      "answer": "മിസിസിപ്പി-മിസൗറി",
      "difficulty": "medium"
    },
    {
      "id": "cow_059",
      "question": "വിസ്തീർണ്ണത്തിൽ ലോകത്തിലെ ഏറ്റവും വലിയ രാജ്യം സ്ഥിതി ചെയ്യുന്ന ഭൂഖണ്ഡങ്ങൾ ഏവ?",
      "options": [
        "ഏഷ്യ, ആഫ്രിക്ക",
        "യൂറോപ്പ്, ഏഷ്യ (റഷ്യ)",
        "ഉത്തര അമേരിക്ക",
        "തെക്കേ അമേരിക്ക"
      ],
      "answer": "യൂറോപ്പ്, ഏഷ്യ (റഷ്യ)",
      "difficulty": "medium"
    },
    {
      "id": "cow_060",
      "question": "ജനസംഖ്യയിൽ രണ്ടാം സ്ഥാനത്തുള്ള ഭൂഖണ്ഡം ഏതാണ്?",
      "options": [
        "യൂറോപ്പ്",
        "ആഫ്രിക്ക",
        "ഉത്തര അമേരിക്ക",
        "തെക്കേ അമേരിക്ക"
      ],
      "answer": "ആഫ്രിക്ക",
      "difficulty": "medium"
    },
    {
      "id": "cow_061",
      "question": "ജനസംഖ്യയിൽ മൂന്നാം സ്ഥാനത്തുള്ള ഭൂഖണ്ഡം ഏതാണ്?",
      "options": [
        "യൂറോപ്പ്",
        "ഉത്തര അമേരിക്ക",
        "തെക്കേ അമേരിക്ക",
        "ആഫ്രിക്ക"
      ],
      "answer": "യൂറോപ്പ്",
      "difficulty": "hard"
    },
    {
      "id": "cow_062",
      "question": "ലോകത്തിലെ ഏറ്റവും നീളം കൂടിയ മലനിരയായ ഗ്രേറ്റ് ഡിവൈഡിംഗ് റേഞ്ച് എവിടെയാണ്?",
      "options": [
        "ആഫ്രിക്ക",
        "ഓസ്‌ട്രേലിയ",
        "ഏഷ്യ",
        "യൂറോപ്പ്"
      ],
      "answer": "ഓസ്‌ട്രേലിയ",
      "difficulty": "medium"
    },
    {
      "id": "cow_063",
      "question": "സഹാറ മരുഭൂമി ആഫ്രിക്കയുടെ ഏത് ഭാഗത്താണ് സ്ഥിതി ചെയ്യുന്നത്?",
      "options": [
        "തെക്ക്",
        "കിഴക്ക്",
        "വടക്ക്",
        "പടിഞ്ഞാറ്"
      ],
      "answer": "വടക്ക്",
      "difficulty": "medium"
    },
    {
      "id": "cow_064",
      "question": "കലഹാരി മരുഭൂമി ഏത് ഭൂഖണ്ഡത്തിലാണ് സ്ഥിതി ചെയ്യുന്നത്?",
      "options": [
        "ഏഷ്യ",
        "ഓസ്‌ട്രേലിയ",
        "ആഫ്രിക്ക",
        "തെക്കേ അമേരിക്ക"
      ],
      "answer": "ആഫ്രിക്ക",
      "difficulty": "medium"
    },
    {
      "id": "cow_065",
      "question": "ഗോബി മരുഭൂമി സ്ഥിതി ചെയ്യുന്നത് ഏത് ഭൂഖണ്ഡത്തിലാണ്?",
      "options": [
        "ആഫ്രിക്ക",
        "ഏഷ്യ",
        "ഓസ്‌ട്രേലിയ",
        "ഉത്തര അമേരിക്ക"
      ],
      "answer": "ഏഷ്യ",
      "difficulty": "easy"
    },
    {
      "id": "cow_066",
      "question": "ലോകത്തിലെ ഏറ്റവും ഉയരത്തിലുള്ള തടാകങ്ങളിൽ ഒന്നായ ടിറ്റിക്കാക്ക തടാകം എവിടെയാണ്?",
      "options": [
        "ആഫ്രിക്ക",
        "ഏഷ്യ",
        "തെക്കേ അമേരിക്ക",
        "യൂറോപ്പ്"
      ],
      "answer": "തെക്കേ അമേരിക്ക",
      "difficulty": "hard"
    },
    {
      "id": "cow_067",
      "question": "അന്റാർട്ടിക്കയിലെ ഏക സജീവ അഗ്നിപർവ്വതം ഏതാണ്?",
      "options": [
        "മൗണ്ട് വിസൂവിയസ്",
        "മൗണ്ട് എറെബസ്",
        "മൗണ്ട് എറ്റ്ന",
        "മൗണ്ട് ഫുജി"
      ],
      "answer": "മൗണ്ട് എറെബസ്",
      "difficulty": "hard"
    },
    {
      "id": "cow_068",
      "question": "ഇന്ത്യയുടെ 'ഭാരതി' ഗവേഷണ കേന്ദ്രം ഏത് ഭൂഖണ്ഡത്തിലാണ് ഉള്ളത്?",
      "options": [
        "ഏഷ്യ",
        "അന്റാർട്ടിക്ക",
        "ആഫ്രിക്ക",
        "ഓസ്‌ട്രേലിയ"
      ],
      "answer": "അന്റാർട്ടിക്ക",
      "difficulty": "medium"
    },
    {
      "id": "cow_069",
      "question": "ഏഷ്യയിലെ ഏറ്റവും ചെറിയ രാജ്യം ഏതാണ്?",
      "options": [
        "സിംഗപ്പൂർ",
        "മാലദ്വീപ്",
        "ഭൂട്ടാൻ",
        "ബഹ്‌റൈൻ"
      ],
      "answer": "മാലദ്വീപ്",
      "difficulty": "easy"
    },
    {
      "id": "cow_070",
      "question": "ആഫ്രിക്കയിലെ ഏറ്റവും ചെറിയ ദ്വീപ് രാജ്യം ഏതാണ്?",
      "options": [
        "മൌറീഷ്യസ്",
        "സെയ്‌ഷെൽസ്",
        "മാഡഗാസ്കർ",
        "കേപ് വെർഡെ"
      ],
      "answer": "സെയ്‌ഷെൽസ്",
      "difficulty": "hard"
    },
    {
      "id": "cow_071",
      "question": "യൂറോപ്പിലെയും ലോകത്തിലെയും ഏറ്റവും ചെറിയ രാജ്യം ഏതാണ്?",
      "options": [
        "മൊണാക്കോ",
        "സാൻ മരീനോ",
        "വത്തിക്കാൻ സിറ്റി",
        "ലിച്ചെൻസ്റ്റൈൻ"
      ],
      "answer": "വത്തിക്കാൻ സിറ്റി",
      "difficulty": "easy"
    },
    {
      "id": "cow_072",
      "question": "തെക്കേ അമേരിക്കയിലെ ഏറ്റവും വലിയ രാജ്യം ഏതാണ്?",
      "options": [
        "അർജന്റീന",
        "ബ്രസീൽ",
        "ചിലി",
        "പെറു"
      ],
      "answer": "ബ്രസീൽ",
      "difficulty": "easy"
    },
    {
      "id": "cow_073",
      "question": "ഉത്തര അമേരിക്കയിലെ ഏറ്റവും വലിയ രാജ്യം ഏതാണ്?",
      "options": [
        "അമേരിക്ക (USA)",
        "കാനഡ",
        "മെക്സിക്കോ",
        "ഗ്രീൻലാൻഡ്"
      ],
      "answer": "കാനഡ",
      "difficulty": "medium"
    },
    {
      "id": "cow_074",
      "question": "ആഫ്രിക്കയിലെ ഏറ്റവും വലിയ രാജ്യം (വിസ്തീർണ്ണത്തിൽ) ഏതാണ്?",
      "options": [
        "സുഡാൻ",
        "അൾജീരിയ",
        "നൈജീരിയ",
        "ഈജിപ്ത്"
      ],
      "answer": "അൾജീരിയ",
      "difficulty": "hard"
    },
    {
      "id": "cow_075",
      "question": "മധ്യരേഖ (Equator) കടന്നുപോകുന്ന ഏഷ്യൻ രാജ്യം ഏതാണ്?",
      "options": [
        "ഇന്ത്യ",
        "ഇന്തോനേഷ്യ",
        "ശ്രീലങ്ക",
        "മലേഷ്യ"
      ],
      "answer": "ഇന്തോനേഷ്യ",
      "difficulty": "medium"
    },
    {
      "id": "cow_076",
      "question": "പ്രസിദ്ധമായ 'ഗ്രേറ്റ് റിഫ്റ്റ് വാലി' (Great Rift Valley) ഏത് ഭൂഖണ്ഡത്തിലാണ്?",
      "options": [
        "ഏഷ്യ",
        "ആഫ്രിക്ക",
        "ഓസ്‌ട്രേലിയ",
        "യൂറോപ്പ്"
      ],
      "answer": "ആഫ്രിക്ക",
      "difficulty": "medium"
    },
    {
      "id": "cow_077",
      "question": "ലോകത്തിലെ ഏറ്റവും നീളമുള്ള ശുദ്ധജല തടാകമായ ടാംഗനിക്ക ഏത് ഭൂഖണ്ഡത്തിലാണ്?",
      "options": [
        "ആഫ്രിക്ക",
        "ഏഷ്യ",
        "ഉത്തര അമേരിക്ക",
        "യൂറോപ്പ്"
      ],
      "answer": "ആഫ്രിക്ക",
      "difficulty": "hard"
    },
    {
      "id": "cow_078",
      "question": "റോക്കി പർവതനിരകൾ (Rocky Mountains) സ്ഥിതി ചെയ്യുന്നത് എവിടെയാണ്?",
      "options": [
        "തെക്കേ അമേരിക്ക",
        "ഉത്തര അമേരിക്ക",
        "യൂറോപ്പ്",
        "ആഫ്രിക്ക"
      ],
      "answer": "ഉത്തര അമേരിക്ക",
      "difficulty": "medium"
    },
    {
      "id": "cow_079",
      "question": "ആൽപ്സ് പർവതനിരകൾ പ്രധാനമായും ഏത് ഭൂഖണ്ഡത്തിലാണ് വ്യാപിച്ചുകിടക്കുന്നത്?",
      "options": [
        "ഏഷ്യ",
        "ഉത്തര അമേരിക്ക",
        "യൂറോപ്പ്",
        "ഓസ്‌ട്രേലിയ"
      ],
      "answer": "യൂറോപ്പ്",
      "difficulty": "easy"
    },
    {
      "id": "cow_080",
      "question": "അറ്റ്‌ലസ് പർവതനിരകൾ (Atlas Mountains) ഏത് ഭൂഖണ്ഡത്തിലാണ്?",
      "options": [
        "ആഫ്രിക്ക",
        "ഏഷ്യ",
        "യൂറോപ്പ്",
        "തെക്കേ അമേരിക്ക"
      ],
      "answer": "ആഫ്രിക്ക",
      "difficulty": "medium"
    },
    {
      "id": "cow_081",
      "question": "ലോകത്തിലെ ഏറ്റവും വലിയ ഉപദ്വീപ് (Peninsula) ആയ അറേബ്യൻ ഉപദ്വീപ് ഏത് ഭൂഖണ്ഡത്തിലാണ്?",
      "options": [
        "ആഫ്രിക്ക",
        "ഏഷ്യ",
        "യൂറോപ്പ്",
        "ഓസ്‌ട്രേലിയ"
      ],
      "answer": "ഏഷ്യ",
      "difficulty": "medium"
    },
    {
      "id": "cow_082",
      "question": "ഏഷ്യയിലെ ഏറ്റവും വലിയ മരുഭൂമി ഏതാണ്?",
      "options": [
        "ഥാർ മരുഭൂമി",
        "അറേബ്യൻ മരുഭൂമി",
        "ഗോബി മരുഭൂമി",
        "സഹാറ മരുഭൂമി"
      ],
      "answer": "അറേബ്യൻ മരുഭൂമി",
      "difficulty": "hard"
    },
    {
      "id": "cow_083",
      "question": "ആഫ്രിക്കയിലെ ഏറ്റവും നീളം കൂടിയ രണ്ടാമത്തെ നദി ഏതാണ്?",
      "options": [
        "നൈജർ നദി",
        "കോംഗോ നദി",
        "സാംബസി നദി",
        "ലിംപോപോ നദി"
      ],
      "answer": "കോംഗോ നദി",
      "difficulty": "hard"
    },
    {
      "id": "cow_084",
      "question": "ഭൂമധ്യരേഖയെ രണ്ട് തവണ മുറിച്ചുകടക്കുന്ന ഒരേയൊരു നദി ഏത് ഭൂഖണ്ഡത്തിലാണ്?",
      "options": [
        "തെക്കേ അമേരിക്ക (ആമസോൺ)",
        "ആഫ്രിക്ക (കോംഗോ നദി)",
        "ഏഷ്യ (ഗംഗ)",
        "ഉത്തര അമേരിക്ക (മിസിസിപ്പി)"
      ],
      "answer": "ആഫ്രിക്ക (കോംഗോ നദി)",
      "difficulty": "hard"
    },
    {
      "id": "cow_085",
      "question": "മകരരേഖയെ (Tropic of Capricorn) രണ്ടുതവണ മുറിച്ചുകടക്കുന്ന ലിംപോപോ നദി എവിടെയാണ്?",
      "options": [
        "ഓസ്‌ട്രേലിയ",
        "ആഫ്രിക്ക",
        "തെക്കേ അമേരിക്ക",
        "ഏഷ്യ"
      ],
      "answer": "ആഫ്രിക്ക",
      "difficulty": "hard"
    },
    {
      "id": "cow_086",
      "question": "ഓസ്‌ട്രേലിയയിലെ ഏറ്റവും വലിയ തടാകം ഏതാണ്?",
      "options": [
        "ബയർ തടാകം",
        "ഇയർ തടാകം (Lake Eyre)",
        "സുപ്പീരിയർ തടാകം",
        "വിക്ടോറിയ തടാകം"
      ],
      "answer": "ഇയർ തടാകം (Lake Eyre)",
      "difficulty": "hard"
    },
    {
      "id": "cow_087",
      "question": "ഒരു ഭൂഖണ്ഡം കൂടിയായ ലോകത്തിലെ ഒരേയൊരു രാജ്യം ഏതാണ്?",
      "options": [
        "ന്യൂസിലാൻഡ്",
        "ഓസ്‌ട്രേലിയ",
        "ഗ്രീൻലാൻഡ്",
        "മഡഗാസ്കർ"
      ],
      "answer": "ഓസ്‌ട്രേലിയ",
      "difficulty": "easy"
    },
    {
      "id": "cow_088",
      "question": "ഏഷ്യയിലെ ഏറ്റവും വലിയ തടാകം ഏതാണ്?",
      "options": [
        "ബൈക്കൽ തടാകം",
        "കാസ്പിയൻ കടൽ",
        "ആരൽ കടൽ",
        "ബൽഖാഷ് തടാകം"
      ],
      "answer": "കാസ്പിയൻ കടൽ",
      "difficulty": "medium"
    },
    {
      "id": "cow_089",
      "question": "ഭൂമിശാസ്ത്രപരമായി ഏറ്റവും പഴയ ഭൂഖണ്ഡഭാഗങ്ങളിൽ ഒന്നായ ഡെക്കാൻ പീഠഭൂമി എവിടെയാണ്?",
      "options": [
        "ആഫ്രിക്ക",
        "ഏഷ്യ",
        "ഓസ്‌ട്രേലിയ",
        "യൂറോപ്പ്"
      ],
      "answer": "ഏഷ്യ",
      "difficulty": "easy"
    },
    {
      "id": "cow_090",
      "question": "ലോകത്തിലെ ഏറ്റവും വലിയ ഉൾനാടൻ ഡെൽറ്റയായ സുന്ദർബൻസ് ഏത് ഭൂഖണ്ഡത്തിലാണ്?",
      "options": [
        "ആഫ്രിക്ക",
        "ഏഷ്യ",
        "ഉത്തര അമേരിക്ക",
        "തെക്കേ അമേരിക്ക"
      ],
      "answer": "ഏഷ്യ",
      "difficulty": "easy"
    },
    {
      "id": "cow_091",
      "question": "യൂറോപ്പിലെ 'punjab' എന്നറിയപ്പെടുന്ന, അഞ്ച് നദികൾ ഒഴുകുന്ന രാജ്യം ഏത് ഭൂഖണ്ഡത്തിലാണ്?",
      "options": [
        "ഏഷ്യ",
        "യൂറോപ്പ്",
        "ആഫ്രിക്ക",
        "ഉത്തര അമേരിക്ക"
      ],
      "answer": "യൂറോപ്പ്",
      "difficulty": "hard"
    },
    {
      "id": "cow_092",
      "question": "യൂറോപ്പിലെ ഏറ്റവും ചെറിയ സ്വതന്ത്ര രാജ്യം വത്തിക്കാൻ ആണെങ്കിൽ രണ്ടാമത്തെ ചെറിയ രാജ്യം ഏതാണ്?",
      "options": [
        "സാൻ മരീനോ",
        "മൊണാക്കോ",
        "ലിച്ചെൻസ്റ്റൈൻ",
        "അൻഡോറ"
      ],
      "answer": "മൊണാക്കോ",
      "difficulty": "hard"
    },
    {
      "id": "cow_093",
      "question": "തെക്കേ അമേരിക്കയിലെ ഏറ്റവും ചെറിയ സ്വതന്ത്ര രാജ്യം ഏതാണ്?",
      "options": [
        "ഉറുഗ്വേ",
        "സുരിനാം",
        "ഗയാന",
        "ഇക്വഡോർ"
      ],
      "answer": "സുരിനാം",
      "difficulty": "hard"
    },
    {
      "id": "cow_094",
      "question": "ഉത്തര അമേരിക്കയിലെ ഏറ്റവും ചെറിയ ദ്വീപ് രാജ്യം ഏതാണ്?",
      "options": [
        "ക്യൂബ",
        "ജമൈക്ക",
        "സെന്റ് കിറ്റ്സ് ആൻഡ് നെവിസ്",
        "ബഹാമാസ്"
      ],
      "answer": "സെന്റ് കിറ്റ്സ് ആൻഡ് നെവിസ്",
      "difficulty": "hard"
    },
    {
      "id": "cow_095",
      "question": "ഏറ്റവും കൂടുതൽ കോഫി ഉത്പാദിപ്പിക്കുന്ന ബ്രസീൽ ഏത് ഭൂഖണ്ഡത്തിലാണ്?",
      "options": [
        "ഉത്തര അമേരിക്ക",
        "തെക്കേ അമേരിക്ക",
        "ആഫ്രിക്ക",
        "ഏഷ്യ"
      ],
      "answer": "തെക്കേ അമേരിക്ക",
      "difficulty": "easy"
    },
    {
      "id": "cow_096",
      "question": "ഭൂമിയിലെ ഏറ്റവും തണുപ്പുകൂടിയ പ്രദേശമായ 'വോസ്റ്റോക്ക് സ്റ്റേഷൻ' എവിടെയാണ്?",
      "options": [
        "യൂറോപ്പ്",
        "ഉത്തര അമേരിക്ക",
        "അന്റാർട്ടിക്ക",
        "ഏഷ്യ"
      ],
      "answer": "അന്റാർട്ടിക്ക",
      "difficulty": "easy"
    },
    {
      "id": "cow_097",
      "question": "പ്രാദേശിക പുൽമേടുകളായ 'വെൽഡ്സ്' (Velds) കാണപ്പെടുന്നത് ഏത് ഭൂഖണ്ഡത്തിലാണ്?",
      "options": [
        "ഓസ്‌ട്രേലിയ",
        "ആഫ്രിക്ക",
        "യൂറോപ്പ്",
        "തെക്കേ അമേരിക്ക"
      ],
      "answer": "ആഫ്രിക്ക",
      "difficulty": "medium"
    },
    {
      "id": "cow_098",
      "question": "ഓസ്‌ട്രേലിയയിലെ പുൽമേടുകൾ അറിയപ്പെടുന്നത് ഏത് പേരിലാണ്?",
      "options": [
        "ഡൗൺസ് (Downs)",
        "സ്റ്റെപ്പീസ്",
        "പ്രയറികൾ",
        "സവന്ന"
      ],
      "answer": "ഡൗൺസ് (Downs)",
      "difficulty": "medium"
    },
    {
      "id": "cow_099",
      "question": "യൂറോപ്പിലും ഏഷ്യയിലുമായി പരന്നുകിടക്കുന്ന പുൽമേടുകൾ ഏവ?",
      "options": [
        "സ്റ്റെപ്പീസ് (Steppes)",
        "പമ്പാസ്",
        "വെൽഡ്സ്",
        "പ്രയറികൾ"
      ],
      "answer": "സ്റ്റെപ്പീസ് (Steppes)",
      "difficulty": "medium"
    },
    {
      "id": "cow_100",
      "question": "ഭൂമിശാസ്ത്രപരമായ വിള്ളൽ കാരണം ഭാവിയിൽ രണ്ട് ഭാഗങ്ങളായി പിരിഞ്ഞുപോകാൻ സാധ്യതയുള്ള ഭൂഖണ്ഡം ഏതാണ്?",
      "options": [
        "അന്റാർട്ടിക്ക",
        "ആഫ്രിക്ക",
        "ഓസ്‌ട്രേലിയ",
        "യൂറോപ്പ്"
      ],
      "answer": "ആഫ്രിക്ക",
      "difficulty": "medium"
    },
    {
      "id": "cow_101",
      "question": "ലോകത്തിലെ ഏറ്റവും നീളമേറിയ റെയിൽവേ പാതയായ ട്രാൻസ്-സൈബീരിയൻ റെയിൽവേ ഏത് ഭൂഖണ്ഡത്തിലാണ്?",
      "options": [
        "യൂറോപ്പ്",
        "ഏഷ്യ",
        "ഉത്തര അമേരിക്ക",
        "ആഫ്രിക്ക"
      ],
      "answer": "ഏഷ്യ",
      "difficulty": "medium"
    },
    {
      "id": "cow_102",
      "question": "പനാമ കനാൽ നിർമ്മിക്കപ്പെട്ടത് ഏത് വർഷമാണ്, ഇത് ഏത് ഭൂഖണ്ഡത്തെ വേർതിരിക്കുന്നു?",
      "options": [
        "1914 (വടക്ക് - തെക്കേ അമേരിക്ക)",
        "1869 (ഏഷ്യ - ആഫ്രിക്ക)",
        "1950 (യൂറോപ്പ് - ആഫ്രിക്ക)",
        "1901 (ഏഷ്യ - യൂറോപ്പ്)"
      ],
      "answer": "1914 (വടക്ക് - തെക്കേ അമേരിക്ക)",
      "difficulty": "hard"
    },
    {
      "id": "cow_103",
      "question": "ഏഷ്യയെയും ഉത്തര അമേരിക്കയെയും തമ്മിൽ വേർതിരിക്കുന്ന കടലിടുക്ക് (Strait) ഏതാണ്?",
      "options": [
        "ജിബ്രാൾട്ടർ കടലിടുക്ക്",
        "ബെറിംഗ് കടലിടുക്ക്",
        "മലാക്ക കടലിടുക്ക്",
        "പാക് കടലിടുക്ക്"
      ],
      "answer": "ബെറിംഗ് കടലിടുക്ക്",
      "difficulty": "hard"
    },
    {
      "id": "cow_104",
      "question": "യൂറോപ്പിനെയും ആഫ്രിക്കയെയും തമ്മിൽ വേർതിരിക്കുന്ന കടലിടുക്ക് ഏതാണ്?",
      "options": [
        "പാക് കടലിടുക്ക്",
        "മലാക്ക കടലിടുക്ക്",
        "ജിബ്രാൾട്ടർ കടലിടുക്ക്",
        "ബെറിംഗ് കടലിടുക്ക്"
      ],
      "answer": "ജിബ്രാൾട്ടർ കടലിടുക്ക്",
      "difficulty": "hard"
    },
    {
      "id": "cow_105",
      "question": "തുർക്കി എന്ന രാജ്യം ഏതെല്ലാം ഭൂഖണ്ഡങ്ങളിലായാണ് സ്ഥിതി ചെയ്യുന്നത്?",
      "options": [
        "ഏഷ്യ, ആഫ്രിക്ക",
        "യൂറോപ്പ്, ഏഷ്യ",
        "യൂറോപ്പ്, ആഫ്രിക്ക",
        "യൂറോപ്പ്, ഉത്തര അമേരിക്ക"
      ],
      "answer": "യൂറോപ്പ്, ഏഷ്യ",
      "difficulty": "medium"
    },
    {
      "id": "cow_106",
      "question": "ഈജിപ്ത് എന്ന രാജ്യം ആഫ്രിക്കയിലാണ്, എന്നാൽ അതിന്റെ സിനായ് പെനിൻസുല ഏത് ഭൂഖണ്ഡത്തിലാണ്?",
      "options": [
        "യൂറോപ്പ്",
        "ഏഷ്യ",
        "ആഫ്രിക്ക",
        "ഓസ്‌ട്രേലിയ"
      ],
      "answer": "ഏഷ്യ",
      "difficulty": "hard"
    },
    {
      "id": "cow_107",
      "question": "ഗ്രേറ്റ് വിക്ടോറിയ മരുഭൂമി സ്ഥിതി ചെയ്യുന്നത് എവിടെയാണ്?",
      "options": [
        "ആഫ്രിക്ക",
        "ഓസ്‌ട്രേലിയ",
        "ഏഷ്യ",
        "തെക്കേ അമേരിക്ക"
      ],
      "answer": "ഓസ്‌ട്രേലിയ",
      "difficulty": "medium"
    },
    {
      "id": "cow_108",
      "question": "ഗിബ്സൺ, സിംപ്സൺ മരുഭൂമികൾ ഏത് ഭൂഖണ്ഡത്തിലാണ് ഉള്ളത്?",
      "options": [
        "ആഫ്രിക്ക",
        "ഏഷ്യ",
        "ഓസ്‌ട്രേലിയ",
        "ഉത്തര അമേരിക്ക"
      ],
      "answer": "ഓസ്‌ട്രേലിയ",
      "difficulty": "hard"
    },
    {
      "id": "cow_109",
      "question": "ലോകത്തിലെ ഏറ്റവും വടക്കേ അറ്റത്തുള്ള ഭൂഖണ്ഡം ഏതാണ്?",
      "options": [
        "യൂറോപ്പ്",
        "ഏഷ്യ",
        "ഉത്തര അമേരിക്ക",
        "അന്റാർട്ടിക്ക"
      ],
      "answer": "ഉത്തര അമേരിക്ക",
      "difficulty": "hard"
    },
    {
      "id": "cow_110",
      "question": "തെക്കേ അമേരിക്കയിലെ ഏറ്റവും വലിയ തടാകം ഏതാണ്?",
      "options": [
        "ടിറ്റിക്കാക്ക തടാകം",
        "മരക്കൈബോ തടാകം (Lake Maracaibo)",
        "ഫർണാണ്ട തടാകം",
        "സുപ്പീരിയർ തടാകം"
      ],
      "answer": "മരക്കൈബോ തടാകം (Lake Maracaibo)",
      "difficulty": "hard"
    },
    {
      "id": "cow_111",
      "question": "ഉത്തര അമേരിക്കയിലെ 'ഗ്രേറ്റ് ലേക്സ്' (Great Lakes) എത്ര തടാകങ്ങൾ ചേർന്നതാണ്?",
      "options": [
        "3",
        "4",
        "5",
        "6"
      ],
      "answer": "5",
      "difficulty": "medium"
    },
    {
      "id": "cow_112",
      "question": "ക്രൂഗർ നാഷണൽ പാർക്ക് ഏത് ഭൂഖണ്ഡത്തിലാണ് സ്ഥിതി ചെയ്യുന്നത്?",
      "options": [
        "ഏഷ്യ",
        "ആഫ്രിക്ക",
        "ഓസ്‌ട്രേലിയ",
        "തെക്കേ അമേരിക്ക"
      ],
      "answer": "ആഫ്രിക്ക",
      "difficulty": "medium"
    },
    {
      "id": "cow_113",
      "question": "ലോകത്തിലെ ഏറ്റവും നീളമുള്ള പവിഴപ്പുറ്റ് ശൃംഖല കാണപ്പെടുന്ന ഭൂഖണ്ഡം ഏതാണ്?",
      "options": [
        "ഏഷ്യ",
        "ആഫ്രിക്ക",
        "ഓസ്‌ട്രേലിയ",
        "ഉത്തര അമേരിക്ക"
      ],
      "answer": "ഓസ്‌ട്രേലിയ",
      "difficulty": "easy"
    },
    {
      "id": "cow_114",
      "question": "അന്റാർട്ടിക്കയിൽ ഇന്ത്യ സ്ഥാപിച്ച രണ്ടാമത്തെ ഗവേഷണ കേന്ദ്രം ഏതാണ്?",
      "options": [
        "ദക്ഷിണ ഗംഗോത്രി",
        "മൈത്രി",
        "ഭാരതി",
        "സാഗർ നിധി"
      ],
      "answer": "മൈത്രി",
      "difficulty": "medium"
    },
    {
      "id": "cow_115",
      "question": "ഏറ്റവും കൂടുതൽ നഗരവൽക്കരിക്കപ്പെട്ട ഭൂഖണ്ഡങ്ങളിൽ മുൻപന്തിയിൽ നിൽക്കുന്നത് ഏതാണ്?",
      "options": [
        "ആഫ്രിക്ക",
        "ഏഷ്യ",
        "യൂറോപ്പ്",
        "തെക്കേ അമേരിക്ക"
      ],
      "answer": "യൂറോപ്പ്",
      "difficulty": "medium"
    },
    {
      "id": "cow_116",
      "question": "പൂർണ്ണമായും ഉത്തരാർദ്ധഗോളത്തിൽ സ്ഥിതി ചെയ്യുന്ന രണ്ട് ഭൂഖണ്ഡങ്ങൾ ഏവ?",
      "options": [
        "ഏഷ്യ, ആഫ്രിക്ക",
        "ഉത്തര അമേരിക്ക, യൂറോപ്പ്",
        "തെക്കേ അമേരിക്ക, ഓസ്ട്രേലിയ",
        "യൂറോപ്പ്, അന്റാർട്ടിക്ക"
      ],
      "answer": "ഉത്തര അമേരിക്ക, യൂറോപ്പ്",
      "difficulty": "hard"
    },
    {
      "id": "cow_117",
      "question": "പൂർണ്ണമായും ദക്ഷിണാർദ്ധഗോളത്തിൽ സ്ഥിതി ചെയ്യുന്ന രണ്ട് ഭൂഖണ്ഡങ്ങൾ ഏവ?",
      "options": [
        "ആഫ്രിക്ക, ഏഷ്യ",
        "ഓസ്‌ട്രേലിയ, അന്റാർട്ടിക്ക",
        "തെക്കേ അമേരിക്ക, യൂറോപ്പ്",
        "ഉത്തര അമേരിക്ക, ഓസ്ട്രേലിയ"
      ],
      "answer": "ഓസ്‌ട്രേലിയ, അന്റാർട്ടിക്ക",
      "difficulty": "medium"
    },
    {
      "id": "cow_118",
      "question": "പ്രാദേശിക മൃഗങ്ങളായ കംഗാരു, കോവാല എന്നിവ ഏത് ഭൂഖണ്ഡത്തിൽ മാത്രം കാണപ്പെടുന്നു?",
      "options": [
        "ആഫ്രിക്ക",
        "ഓസ്‌ട്രേലിയ",
        "തെക്കേ അമേരിക്ക",
        "അന്റാർട്ടിക്ക"
      ],
      "answer": "ഓസ്‌ട്രേലിയ",
      "difficulty": "easy"
    },
    {
      "id": "cow_119",
      "question": "അനക്കോണ്ട പാമ്പുകൾ സ്വാഭാവികമായി കാണപ്പെടുന്നത് ഏത് ഭൂഖണ്ഡത്തിലെ കാടുകളിലാണ്?",
      "options": [
        "ആഫ്രിക്ക",
        "ഏഷ്യ",
        "തെക്കേ അമേരിക്ക",
        "ഓസ്‌ട്രേലിയ"
      ],
      "answer": "തെക്കേ അമേരിക്ക",
      "difficulty": "easy"
    },
    {
      "id": "cow_120",
      "question": "ലോകത്തിലെ ഏറ്റവും വീതികൂടിയ വെള്ളച്ചാട്ടമായ ഖോൺ വെള്ളച്ചാട്ടം (Khone Falls) ഏത് ഭൂഖണ്ഡത്തിലാണ്?",
      "options": [
        "ആഫ്രിക്ക",
        "ഏഷ്യ",
        "തെക്കേ അമേരിക്ക",
        "ഉത്തര അമേരിക്ക"
      ],
      "answer": "ഏഷ്യ",
      "difficulty": "hard"
    },
    {
      "id": "cow_121",
      "question": "ലോകത്തിലെ ഏറ്റവും ഉയരത്തിലുള്ള സജീവ അഗ്നിപർവ്വതമായ 'ഓഹോസ് ഡെൽ സലാഡോ' എവിടെയാണ്?",
      "options": [
        "ഉത്തര അമേരിക്ക",
        "തെക്കേ അമേരിക്ക",
        "യൂറോപ്പ്",
        "ഏഷ്യ"
      ],
      "answer": "തെക്കേ അമേരിക്ക",
      "difficulty": "hard"
    },
    {
      "id": "cow_122",
      "question": "ഗ്രീൻലാൻഡ് ദ്വീപിന്റെ ഭരണം കൈയാളുന്ന ഡെന്മാർക്ക് ഏത് ഭൂഖണ്ഡത്തിലെ രാജ്യമാണ്?",
      "options": [
        "ഉത്തര അമേരിക്ക",
        "യൂറോപ്പ്",
        "ഏഷ്യ",
        "ആഫ്രിക്ക"
      ],
      "answer": "യൂറോപ്പ്",
      "difficulty": "medium"
    },
    {
      "id": "cow_123",
      "question": "ഏറ്റവും നീളമുള്ള തീരപ്രദേശമുള്ള ഭൂഖണ്ഡം ഏതാണ്?",
      "options": [
        "ആഫ്രിക്ക",
        "ഏഷ്യ",
        "ഉത്തര അമേരിക്ക",
        "യൂറോപ്പ്"
      ],
      "answer": "ഏഷ്യ",
      "difficulty": "hard"
    },
    {
      "id": "cow_124",
      "question": "ഭൂമിയിലെ ഏറ്റവും വലിയ താപനില വ്യത്യാസങ്ങൾ അനുഭവപ്പെടുന്ന സൈബീരിയ ഏത് ഭൂഖണ്ഡത്തിലാണ്?",
      "options": [
        "യൂറോപ്പ്",
        "ഏഷ്യ",
        "ഉത്തര അമേരിക്ക",
        "അന്റാർട്ടിക്ക"
      ],
      "answer": "ഏഷ്യ",
      "difficulty": "easy"
    },
    {
      "id": "cow_125",
      "question": "ഏഷ്യയിലെ ഏറ്റവും ജനസംഖ്യ കുറഞ്ഞ രാജ്യം ഏതാണ്?",
      "options": [
        "ഭൂട്ടാൻ",
        "മാലദ്വീപ്",
        "ബ്രൂണൈ",
        "മംഗോളിയ"
      ],
      "answer": "മാലദ്വീപ്",
      "difficulty": "medium"
    },
    {
      "id": "cow_126",
      "question": "ലൂസിഫർ അഥവാ 'ഡെത്ത് വാലി' (Death Valley) എന്നറിയപ്പെടുന്ന ഏറ്റവും ചൂടുകൂടിയ സ്ഥലം ഏത് ഭൂഖണ്ഡത്തിലാണ്?",
      "options": [
        "ആഫ്രിക്ക",
        "ഏഷ്യ",
        "ഓസ്‌ട്രേലിയ",
        "ഉത്തര അമേരിക്ക"
      ],
      "answer": "ഉത്തര അമേരിക്ക",
      "difficulty": "medium"
    },
    {
      "id": "cow_127",
      "question": "ആഫ്രിക്കയിലെ ഏറ്റവും നീളം കൂടിയ പർവതനിര ഏതാണ്?",
      "options": [
        "ഡ്രാക്കൻസ്ബർഗ്",
        "അറ്റ്‌ലസ് പർവതനിരകൾ",
        "കിളിമഞ്ചാരോ",
        "റുവൻസോറി"
      ],
      "answer": "അറ്റ്‌ലസ് പർവതനിരകൾ",
      "difficulty": "medium"
    },
    {
      "id": "cow_128",
      "question": "സൂയസ് കനാൽ മെഡിറ്ററേനിയൻ കടലിനെ ഏത് കടലുമായി ബന്ധിപ്പിക്കുന്നു?",
      "options": [
        "കരിങ്കടൽ",
        "ചെങ്കടൽ (Red Sea)",
        "അറബിക്കടൽ",
        "കാസ്പിയൻ കടൽ"
      ],
      "answer": "ചെങ്കടൽ (Red Sea)",
      "difficulty": "medium"
    },
    {
      "id": "cow_129",
      "question": "യൂറോപ്പിലെ പ്രശസ്തമായ ലണ്ടൻ നഗരം ഏത് നദിക്കരയിലാണ് സ്ഥിതി ചെയ്യുന്നത്?",
      "options": [
        "സീൻ നദി",
        "ഡാന്യൂബ്",
        "തേംസ് നദി",
        "റൈൻ"
      ],
      "answer": "തേംസ് നദി",
      "difficulty": "easy"
    },
    {
      "id": "cow_130",
      "question": "ഫ്രാൻസിന്റെ തലസ്ഥാനമായ പാരീസ് ഏത് നദിക്കരയിലാണ് സ്ഥിതി ചെയ്യുന്നത്?",
      "options": [
        "തേംസ്",
        "സീൻ നദി (Seine)",
        "വോൾഗ",
        "ടൈബർ"
      ],
      "answer": "സീൻ നദി (Seine)",
      "difficulty": "medium"
    },
    {
      "id": "cow_131",
      "question": "ഇറ്റലിയുടെ തലസ്ഥാനമായ റോം ഏത് നദിക്കരയിലാണ് സ്ഥിതി ചെയ്യുന്നത്?",
      "options": [
        "ടൈബർ നദി (Tiber)",
        "പോ നദി",
        "റൈൻ",
        "ഡാന്യൂബ്"
      ],
      "answer": "ടൈബർ നദി (Tiber)",
      "difficulty": "hard"
    },
    {
      "id": "cow_132",
      "question": "പൂർണ്ണമായും കരയാൽ ചുറ്റപ്പെട്ട (Landlocked) ഏറ്റവും വലിയ രാജ്യം കസാക്കിസ്ഥാൻ ഏത് ഭൂഖണ്ഡത്തിലാണ്?",
      "options": [
        "യൂറോപ്പ്",
        "ഏഷ്യ",
        "ആഫ്രിക്ക",
        "തെക്കേ അമേരിക്ക"
      ],
      "answer": "ഏഷ്യ",
      "difficulty": "medium"
    },
    {
      "id": "cow_133",
      "question": "തെക്കേ അമേരിക്കയിലെ കരയാൽ ചുറ്റപ്പെട്ട (Landlocked) രണ്ട് രാജ്യങ്ങൾ ഏവ?",
      "options": [
        "ബ്രസീൽ, അർജന്റീന",
        "ബൊളീവിയ, പരാഗ്വേ",
        "പെറു, ചിലി",
        "കൊളംബിയ, ഇക്വഡോർ"
      ],
      "answer": "ബൊളീവിയ, പരാഗ്വേ",
      "difficulty": "hard"
    },
    {
      "id": "cow_134",
      "question": "ഉത്തര അമേരിക്കൻ ഭൂഖണ്ഡത്തിൽ കരയാൽ ചുറ്റപ്പെട്ട (Landlocked) എത്ര രാജ്യങ്ങളുണ്ട്?",
      "options": [
        "ഒന്നുമില്ല (0)",
        "2",
        "5",
        "1"
      ],
      "answer": "ഒന്നുമില്ല (0)",
      "difficulty": "hard"
    },
    {
      "id": "cow_135",
      "question": "അപ്പലേച്ചിയൻ പർവതനിരകൾ (Appalachian Mountains) ഏത് ഭൂഖണ്ഡത്തിലാണ് ഉള്ളത്?",
      "options": [
        "യൂറോപ്പ്",
        "ഏഷ്യ",
        "ഉത്തര അമേരിക്ക",
        "ഓസ്‌ട്രേലിയ"
      ],
      "answer": "ഉത്തര അമേരിക്ക",
      "difficulty": "hard"
    },
    {
      "id": "cow_136",
      "question": "ലോകത്തിലെ ഏറ്റവും വലിയ ഉപദ്വീപീയ ഭൂഖണ്ഡം (Peninsular Continent) എന്ന് വിളിക്കപ്പെടുന്നത് ഏതിനെയാണ്?",
      "options": [
        "ഏഷ്യ",
        "യൂറോപ്പ്",
        "ആഫ്രിക്ക",
        "ഓസ്‌ട്രേലിയ"
      ],
      "answer": "യൂറോപ്പ്",
      "difficulty": "medium"
    },
    {
      "id": "cow_137",
      "question": "ആഫ്രിക്കൻ ഭൂഖണ്ഡത്തിന്റെ ഏറ്റവും തെക്കേ അറ്റത്തുള്ള മുനമ്പ് ഏതാണ്?",
      "options": [
        "കേപ് ഓഫ് ഗുഡ് ഹോപ്പ് (കേപ് അഗുൽഹാസ്)",
        "കേപ് കോമോറിൻ",
        "കേപ് ഹോൺ",
        "കേപ് യോർക്ക്"
      ],
      "answer": "കേപ് ഓഫ് ഗുഡ് ഹോപ്പ് (കേപ് അഗുൽഹാസ്)",
      "difficulty": "medium"
    },
    {
      "id": "cow_138",
      "question": "തെക്കേ അമേരിക്കയുടെ ഏറ്റവും തെക്കേ അറ്റത്തുള്ള മുനമ്പ് ഏതാണ്?",
      "options": [
        "കേപ് ഓഫ് ഗുഡ് ഹോപ്പ്",
        "കേപ് ഹോൺ (Cape Horn)",
        "കേപ് അഗുൽഹാസ്",
        "കേപ് ലീവിൻ"
      ],
      "answer": "കേപ് ഹോൺ (Cape Horn)",
      "difficulty": "hard"
    },
    {
      "id": "cow_139",
      "question": "ഏറ്റവും കൂടുതൽ വജ്രം, സ്വർണ്ണം എന്നിവ ഉത്പാദിപ്പിക്കുന്ന ഖനികൾ ഉള്ള ഭൂഖണ്ഡം ഏതാണ്?",
      "options": [
        "ഏഷ്യ",
        "ആഫ്രിക്ക",
        "ഓസ്‌ട്രേലിയ",
        "ഉത്തര അമേരിക്ക"
      ],
      "answer": "ആഫ്രിക്ക",
      "difficulty": "easy"
    },
    {
      "id": "cow_140",
      "question": "മാഡഗാസ്കർ ദ്വീപ് ഏത് ഭൂഖണ്ഡത്തിന്റെ ഭാഗമായാണ് കണക്കാക്കുന്നത്?",
      "options": [
        "ഏഷ്യ",
        "ആഫ്രിക്ക",
        "ഓസ്‌ട്രേലിയ",
        "യൂറോപ്പ്"
      ],
      "answer": "ആഫ്രിക്ക",
      "difficulty": "easy"
    },
    {
      "id": "cow_141",
      "question": "ലോകത്തിൽ ഏറ്റവും കൂടുതൽ ഭാഷകൾ സംസാരിക്കപ്പെടുന്ന ഭൂഖണ്ഡം ഏതാണ്?",
      "options": [
        "യൂറോപ്പ്",
        "ആഫ്രിക്ക",
        "ഏഷ്യ",
        "തെക്കേ അമേരിക്ക"
      ],
      "answer": "ഏഷ്യ",
      "difficulty": "hard"
    },
    {
      "id": "cow_142",
      "question": "ഒരു രാജ്യവും ഇല്ലാത്ത ഒരേയൊരു ഭൂഖണ്ഡം ഏതാണ്?",
      "options": [
        "ഓസ്‌ട്രേലിയ",
        "അന്റാർട്ടിക്ക",
        "യൂറോപ്പ്",
        "തെക്കേ അമേരിക്ക"
      ],
      "answer": "അന്റാർട്ടിക്ക",
      "difficulty": "easy"
    },
    {
      "id": "cow_143",
      "question": "ഓസ്‌ട്രേലിയൻ ഭൂഖണ്ഡത്തിലെ ഏറ്റവും വലിയ നഗരം ഏതാണ്?",
      "options": [
        "മെൽബൺ",
        "സിഡ്നി",
        "കാൻബെറ",
        "ബ്രിസ്ബേൻ"
      ],
      "answer": "സിഡ്നി",
      "difficulty": "medium"
    },
    {
      "id": "cow_144",
      "question": "ഏറ്റവും നീളം കൂടിയ മൂന്നാമത്തെ നദിയായ യാങ്‌സി ഏത് രാജ്യത്തിലൂടെയാണ് ഒഴുകുന്നത്?",
      "options": [
        "ഇന്ത്യ",
        "ചൈന",
        "റഷ്യ",
        "ജപ്പാൻ"
      ],
      "answer": "ചൈന",
      "difficulty": "easy"
    },
    {
      "id": "cow_145",
      "question": "വടക്കേ അമേരിക്കയിലെ ഏറ്റവും വലിയ വെള്ളച്ചാട്ട വ്യൂഹം ഏതാണ്?",
      "options": [
        "എയ്ഞ്ചൽ വെള്ളച്ചാട്ടം",
        "നയാഗ്ര വെള്ളച്ചാട്ടം",
        "വിക്ടോറിയ വെള്ളച്ചാട്ടം",
        "ഇഗ്വാസു വെള്ളച്ചാട്ടം"
      ],
      "answer": "നയാഗ്ര വെള്ളച്ചാട്ടം",
      "difficulty": "easy"
    },
    {
      "id": "cow_146",
      "question": "ബ്രസീലും അർജന്റീനയും പങ്കിടുന്ന ലോകപ്രശസ്തമായ വെള്ളച്ചാട്ടം ഏതാണ്?",
      "options": [
        "എയ്ഞ്ചൽ വെള്ളച്ചാട്ടം",
        "ഇഗ്വാസു വെള്ളച്ചാട്ടം (Iguazu Falls)",
        "നയാഗ്ര",
        "വിക്ടോറിയ"
      ],
      "answer": "ഇഗ്വാസു വെള്ളച്ചാട്ടം (Iguazu Falls)",
      "difficulty": "hard"
    },
    {
      "id": "cow_147",
      "question": "ഏഷ്യയിലെ ഏറ്റവും വലിയ ശുദ്ധജല തടാകങ്ങളിൽ ഒന്നായ വൂളാർ തടാകം (Wular Lake) ഏത് രാജ്യത്താണ്?",
      "options": [
        "ചൈന",
        "ഇന്ത്യ",
        "പാകിസ്ഥാൻ",
        "ബംഗ്ലാദേശ്"
      ],
      "answer": "ഇന്ത്യ",
      "difficulty": "easy"
    },
    {
      "id": "cow_148",
      "question": "ഭൂമിശാസ്ത്രപരമായി 'ഹോൺ ഓഫ് ആഫ്രിക്ക' (Horn of Africa) എന്നറിയപ്പെടുന്ന ഭാഗത്ത് ഉൾപ്പെടാത്ത രാജ്യം ഏതാണ്?",
      "options": [
        "സൊമാലിയ",
        "എത്യോപ്യ",
        "ജിബൂട്ടി",
        "ദക്ഷിണാഫ്രിക്ക"
      ],
      "answer": "ദക്ഷിണാഫ്രിക്ക",
      "difficulty": "hard"
    },
    {
      "id": "cow_149",
      "question": "പൂർണ്ണമായും മഞ്ഞുമൂടിക്കിടക്കുന്നതിനാൽ 'ഉറഞ്ഞുപോയ ഭൂഖണ്ഡം' (Frozen Continent) എന്ന് വിളിക്കുന്നത് ഏതിനെയാണ്?",
      "options": [
        "യൂറോപ്പ്",
        "ഉത്തര അമേരിക്ക",
        "അന്റാർട്ടിക്ക",
        "ഓസ്‌ട്രേലിയ"
      ],
      "answer": "അന്റാർട്ടിക്ക",
      "difficulty": "easy"
    },
    {
      "id": "cow_151",
      "question": "ഏഷ്യയിലെ ഏറ്റവും നീളം കൂടിയ രണ്ടാമത്തെ നദി ഏതാണ്?",
      "options": [
        "സിന്ധു നദി",
        "ഹോയാങ് ഹെ (മഞ്ഞനദി)",
        "മേകോങ് നദി",
        "ബ്രഹ്മപുത്ര"
      ],
      "answer": "ഹോയാങ് ഹെ (മഞ്ഞനദി)",
      "difficulty": "hard"
    }
  ]
}