{
  "questions": [
    {
      "id": "io_001",
      "question": "IMF പ്രധാനമായി ഏത് മേഖലയിലാണ് പ്രവർത്തിക്കുന്നത്?",
      "options": [
        "1863",
        "അന്തർദേശീയ പോലീസ് സഹകരണം",
        "മാനവിക സഹായം",
        "അന്തർദേശീയ നാണയ സഹകരണം"
      ],
      "answer": "അന്തർദേശീയ നാണയ സഹകരണം",
      "difficulty": "medium"
    },
    {
      "id": "io_002",
      "question": "BRICS പ്രധാനമായി ഏത് മേഖലയിലാണ് പ്രവർത്തിക്കുന്നത്?",
      "options": [
        "ലോസാൻ",
        "1904",
        "അന്തർദേശീയ ഫുട്ബോൾ നിയന്ത്രണം",
        "ഉദയോന്മുഖ സാമ്പത്തിക രാജ്യങ്ങളുടെ കൂട്ടായ്മ"
      ],
      "answer": "ഉദയോന്മുഖ സാമ്പത്തിക രാജ്യങ്ങളുടെ കൂട്ടായ്മ",
      "difficulty": "medium"
    },
    {
      "id": "io_003",
      "question": "ASEAN സ്ഥാപിതമായത് ഏത് വർഷത്തിലാണ്?",
      "options": [
        "1948",
        "1967",
        "ആഗോള ആരോഗ്യ പ്രവർത്തനങ്ങൾ",
        "പാരിസ്"
      ],
      "answer": "1967",
      "difficulty": "medium"
    },
    {
      "id": "io_004",
      "question": "SAARC പ്രധാനമായി ഏത് മേഖലയിലാണ് പ്രവർത്തിക്കുന്നത്?",
      "options": [
        "1991",
        "ദക്ഷിണേഷ്യൻ പ്രാദേശിക സഹകരണം",
        "യൂറോപ്പിലെ സുരക്ഷ സഹകരണം",
        "മോണ്ടെവിഡിയോ"
      ],
      "answer": "ദക്ഷിണേഷ്യൻ പ്രാദേശിക സഹകരണം",
      "difficulty": "medium"
    },
    {
      "id": "io_005",
      "question": "WTO പ്രധാനമായി ഏത് മേഖലയിലാണ് പ്രവർത്തിക്കുന്നത്?",
      "options": [
        "കരീബിയൻ സമൂഹം",
        "ആഗോള വ്യാപാര നിയമങ്ങൾ",
        "സ്യൂറിക്",
        "മാനവിക അടിയന്തിര സഹായം"
      ],
      "answer": "ആഗോള വ്യാപാര നിയമങ്ങൾ",
      "difficulty": "medium"
    },
    {
      "id": "io_006",
      "question": "Commonwealth സ്ഥാപിതമായത് ഏത് വർഷത്തിലാണ്?",
      "options": [
        "1919",
        "തൊഴിൽ മാനദണ്ഡങ്ങൾ",
        "വാഷിങ്ടൺ ഡി.സി.",
        "1931"
      ],
      "answer": "1931",
      "difficulty": "medium"
    },
    {
      "id": "io_007",
      "question": "UNICEF പ്രധാനമായി ഏത് മേഖലയിലാണ് പ്രവർത്തിക്കുന്നത്?",
      "options": [
        "1950",
        "കുട്ടികളുടെ ക്ഷേമം",
        "അന്തർദേശീയ കടൽസുരക്ഷ",
        "കാലാവസ്ഥാ സഹകരണം"
      ],
      "answer": "കുട്ടികളുടെ ക്ഷേമം",
      "difficulty": "medium"
    },
    {
      "id": "io_008",
      "question": "UNESCO പ്രധാനമായി ഏത് മേഖലയിലാണ് പ്രവർത്തിക്കുന്നത്?",
      "options": [
        "വിദ്യാഭ്യാസം, ശാസ്ത്രം, സംസ്കാരം",
        "സ്യൂറിക്",
        "1904",
        "അന്തർദേശീയ ഫുട്ബോൾ നിയന്ത്രണം"
      ],
      "answer": "വിദ്യാഭ്യാസം, ശാസ്ത്രം, സംസ്കാരം",
      "difficulty": "medium"
    },
    {
      "id": "io_009",
      "question": "OPEC ആസ്ഥാനം ഏത്?",
      "options": [
        "റിയാദ്",
        "വിയന്ന",
        "ടെഹ്റാൻ",
        "ദുബായ്"
      ],
      "answer": "വിയന്ന",
      "difficulty": "medium"
    },
    {
      "id": "io_010",
      "question": "African Union പ്രധാനമായി ഏത് മേഖലയിലാണ് പ്രവർത്തിക്കുന്നത്?",
      "options": [
        "1904",
        "ആഫ്രിക്കൻ രാജ്യങ്ങളുടെ കൂട്ടായ്മ",
        "മാനവിക അടിയന്തിര സഹായം",
        "സ്യൂറിക്"
      ],
      "answer": "ആഫ്രിക്കൻ രാജ്യങ്ങളുടെ കൂട്ടായ്മ",
      "difficulty": "medium"
    },
    {
      "id": "io_011",
      "question": "WHO പ്രധാനമായി ഏത് മേഖലയിലാണ് പ്രവർത്തിക്കുന്നത്?",
      "options": [
        "ദക്ഷിണ അമേരിക്കൻ വിപണി കൂട്ടായ്മ",
        "മോണ്ടെവിഡിയോ",
        "1991",
        "ആഗോള ആരോഗ്യ പ്രവർത്തനങ്ങൾ"
      ],
      "answer": "ആഗോള ആരോഗ്യ പ്രവർത്തനങ്ങൾ",
      "difficulty": "medium"
    },
    {
      "id": "io_012",
      "question": "ILO സ്ഥാപിതമായ വർഷം ഏത്?",
      "options": [
        "1919",
        "1950",
        "1945",
        "2000"
      ],
      "answer": "1919",
      "difficulty": "medium"
    },
    {
      "id": "io_013",
      "question": "NATO പ്രധാനമായി ഏത് മേഖലയിലാണ് പ്രവർത്തിക്കുന്നത്?",
      "options": [
        "സൈനിക കൂട്ടായ്മ",
        "അവസരസൗകര്യ ധനസഹായം",
        "2015",
        "ഷാങ്ഹായ്"
      ],
      "answer": "സൈനിക കൂട്ടായ്മ",
      "difficulty": "medium"
    },
    {
      "id": "io_014",
      "question": "ILO പ്രധാനമായി ഏത് മേഖലയിലാണ് പ്രവർത്തിക്കുന്നത്?",
      "options": [
        "1894",
        "ന്യൂയോർക്ക്",
        "തൊഴിൽ മാനദണ്ഡങ്ങൾ",
        "ഒളിമ്പിക് പ്രസ്ഥാന നിയന്ത്രണം"
      ],
      "answer": "തൊഴിൽ മാനദണ്ഡങ്ങൾ",
      "difficulty": "medium"
    },
    {
      "id": "io_015",
      "question": "EUയുടെ ആസ്ഥാനം എവിടെയാണ്?",
      "options": [
        "ഏഷ്യൻ വികസന ധനസഹായം",
        "1966",
        "മനില",
        "ബ്രസ്സൽസ്"
      ],
      "answer": "ബ്രസ്സൽസ്",
      "difficulty": "medium"
    },
    {
      "id": "io_016",
      "question": "ASEAN പ്രധാനമായി ഏത് മേഖലയിലാണ് പ്രവർത്തിക്കുന്നത്?",
      "options": [
        "1972",
        "തെക്കുകിഴക്കൻ ഏഷ്യൻ സഹകരണം",
        "നായ്റോബി",
        "വികസന പരിപാടികൾ"
      ],
      "answer": "തെക്കുകിഴക്കൻ ഏഷ്യൻ സഹകരണം",
      "difficulty": "medium"
    },
    {
      "id": "io_017",
      "question": "UN പ്രധാനമായി ഏത് മേഖലയിലാണ് പ്രവർത്തിക്കുന്നത്?",
      "options": [
        "യൂറോപ്പിലെ സുരക്ഷ സഹകരണം",
        "കെയ്റോ",
        "ആഗോള സമാധാനവും സഹകരണവും",
        "അറബ് രാജ്യങ്ങളുടെ സഹകരണം"
      ],
      "answer": "ആഗോള സമാധാനവും സഹകരണവും",
      "difficulty": "medium"
    },
    {
      "id": "io_018",
      "question": "NATOയുടെ ആസ്ഥാനം എവിടെയാണ്?",
      "options": [
        "1949",
        "സൈനിക കൂട്ടായ്മ",
        "ബ്രസ്സൽസ്",
        "1993"
      ],
      "answer": "ബ്രസ്സൽസ്",
      "difficulty": "medium"
    },
    {
      "id": "io_019",
      "question": "OPEC പ്രധാനമായി ഏത് മേഖലയിലാണ് പ്രവർത്തിക്കുന്നത്?",
      "options": [
        "നായ്റോബി",
        "1965",
        "എണ്ണ കയറ്റുമതി രാജ്യങ്ങളുടെ സംഘടന",
        "വികസന പരിപാടികൾ"
      ],
      "answer": "എണ്ണ കയറ്റുമതി രാജ്യങ്ങളുടെ സംഘടന",
      "difficulty": "medium"
    },
    {
      "id": "io_020",
      "question": "EU പ്രധാനമായി ഏത് മേഖലയിലാണ് പ്രവർത്തിക്കുന്നത്?",
      "options": [
        "റോം",
        "കുട്ടികളുടെ ക്ഷേമം",
        "1946",
        "യൂറോപ്യൻ രാഷ്ട്രീയ-സാമ്പത്തിക കൂട്ടായ്മ"
      ],
      "answer": "യൂറോപ്യൻ രാഷ്ട്രീയ-സാമ്പത്തിക കൂട്ടായ്മ",
      "difficulty": "medium"
    },
    {
      "id": "io_021",
      "question": "SAARCയുടെ ആസ്ഥാനം എവിടെയാണ്?",
      "options": [
        "ഷാങ്ഹായ്",
        "അവസരസൗകര്യ ധനസഹായം",
        "2015",
        "കാഠ്മണ്ഡു"
      ],
      "answer": "കാഠ്മണ്ഡു",
      "difficulty": "medium"
    },
    {
      "id": "io_022",
      "question": "FAO പ്രധാനമായി ഏത് മേഖലയിലാണ് പ്രവർത്തിക്കുന്നത്?",
      "options": [
        "ജക്കാർത്ത",
        "1967",
        "ഭക്ഷ്യവും കൃഷിയും",
        "തെക്കുകിഴക്കൻ ഏഷ്യൻ സഹകരണം"
      ],
      "answer": "ഭക്ഷ്യവും കൃഷിയും",
      "difficulty": "medium"
    },
    {
      "id": "io_023",
      "question": "World Bank പ്രധാനമായി ഏത് മേഖലയിലാണ് പ്രവർത്തിക്കുന്നത്?",
      "options": [
        "വികസന ധനസഹായം",
        "1995",
        "1944",
        "അന്തർദേശീയ നാണയ സഹകരണം"
      ],
      "answer": "വികസന ധനസഹായം",
      "difficulty": "medium"
    },
    {
      "id": "io_024",
      "question": "EU ആസ്ഥാനം ഏത്?",
      "options": [
        "ലണ്ടൻ",
        "Brussels",
        "പാരീസ്",
        "റോം"
      ],
      "answer": "Brussels",
      "difficulty": "medium"
    },
    {
      "id": "io_025",
      "question": "UNHCR സ്ഥാപിതമായ വർഷം ഏത്?",
      "options": [
        "1945",
        "1970",
        "1950",
        "1960"
      ],
      "answer": "1950",
      "difficulty": "medium"
    },
    {
      "id": "io_026",
      "question": "SAARC ആസ്ഥാനം ഏത്?",
      "options": [
        "കൊളംബോ",
        "കാഠ്മണ്ഡു",
        "ഡൽഹി",
        "ഢാക്ക"
      ],
      "answer": "കാഠ്മണ്ഡു",
      "difficulty": "medium"
    },
    {
      "id": "io_027",
      "question": "UNICEF സ്ഥാപിതമായത് ഏത് വർഷത്തിലാണ്?",
      "options": [
        "സിംഗപ്പൂർ സെക്രട്ടറിയറ്റ്",
        "1946",
        "BRICS വികസന ബാങ്ക്",
        "2015"
      ],
      "answer": "1946",
      "difficulty": "medium"
    },
    {
      "id": "io_028",
      "question": "FAOയുടെ ആസ്ഥാനം എവിടെയാണ്?",
      "options": [
        "ലിയോൺ",
        "റോം",
        "അന്തർദേശീയ പോലീസ് സഹകരണം",
        "1923"
      ],
      "answer": "റോം",
      "difficulty": "medium"
    },
    {
      "id": "io_029",
      "question": "UN സുരക്ഷാ കൗൺസിലിലെ സ്ഥിരം അംഗങ്ങളുടെ എണ്ണം?",
      "options": [
        "10",
        "5",
        "7",
        "15"
      ],
      "answer": "5",
      "difficulty": "easy"
    },
    {
      "id": "io_030",
      "question": "World Bank സ്ഥാപിതമായ വർഷം ഏത്?",
      "options": [
        "1945",
        "1960",
        "1950",
        "1944"
      ],
      "answer": "1944",
      "difficulty": "medium"
    },
    {
      "id": "io_031",
      "question": "UNESCOയുടെ ആസ്ഥാനം എവിടെയാണ്?",
      "options": [
        "ഏഷ്യൻ വികസന ധനസഹായം",
        "2016",
        "ബീജിംഗ്",
        "പാരിസ്"
      ],
      "answer": "പാരിസ്",
      "difficulty": "medium"
    },
    {
      "id": "io_032",
      "question": "FAO സ്ഥാപിതമായ വർഷം ഏത്?",
      "options": [
        "1944",
        "1950",
        "1945",
        "1960"
      ],
      "answer": "1945",
      "difficulty": "medium"
    },
    {
      "id": "io_033",
      "question": "ILO ആസ്ഥാനം ഏത്?",
      "options": [
        "റോം",
        "ജനീവ",
        "പാരീസ്",
        "ന്യൂയോർക്ക്"
      ],
      "answer": "ജനീവ",
      "difficulty": "medium"
    },
    {
      "id": "io_034",
      "question": "FAO സ്ഥാപിതമായത് ഏത് വർഷത്തിലാണ്?",
      "options": [
        "2002",
        "ആഫ്രിക്കൻ രാജ്യങ്ങളുടെ കൂട്ടായ്മ",
        "1945",
        "അഡിസ് അബാബ"
      ],
      "answer": "1945",
      "difficulty": "medium"
    },
    {
      "id": "io_035",
      "question": "IMF സ്ഥാപിതമായത് ഏത് വർഷത്തിലാണ്?",
      "options": [
        "1949",
        "1993",
        "1944",
        "സൈനിക കൂട്ടായ്മ"
      ],
      "answer": "1944",
      "difficulty": "medium"
    },
    {
      "id": "io_036",
      "question": "NATO സ്ഥാപിതമായത് ഏത് വർഷത്തിലാണ്?",
      "options": [
        "1863",
        "1949",
        "മാനവിക സഹായം",
        "അന്തർദേശീയ പോലീസ് സഹകരണം"
      ],
      "answer": "1949",
      "difficulty": "medium"
    },
    {
      "id": "io_037",
      "question": "WHOയുടെ ആസ്ഥാനം എവിടെയാണ്?",
      "options": [
        "ആഫ്രിക്കൻ രാജ്യങ്ങളുടെ കൂട്ടായ്മ",
        "ജിനീവ",
        "2002",
        "ലണ്ടൻ"
      ],
      "answer": "ജിനീവ",
      "difficulty": "medium"
    },
    {
      "id": "io_038",
      "question": "IAEA സ്ഥാപിതമായ വർഷം ഏത്?",
      "options": [
        "1960",
        "1957",
        "1970",
        "1945"
      ],
      "answer": "1957",
      "difficulty": "medium"
    },
    {
      "id": "io_039",
      "question": "റെഡ് ക്രോസ് (ICRC) ആസ്ഥാനം?",
      "options": [
        "റോം",
        "ജനീവ",
        "പാരീസ്",
        "ന്യൂയോർക്ക്"
      ],
      "answer": "ജനീവ",
      "difficulty": "medium"
    },
    {
      "id": "io_040",
      "question": "SAARC അംഗങ്ങളുടെ എണ്ണം?",
      "options": [
        "12",
        "5",
        "10",
        "8"
      ],
      "answer": "8",
      "difficulty": "medium"
    },
    {
      "id": "io_041",
      "question": "African Union സ്ഥാപിതമായത് ഏത് വർഷത്തിലാണ്?",
      "options": [
        "2002",
        "1931",
        "ആഫ്രിക്കൻ രാജ്യങ്ങളുടെ കൂട്ടായ്മ",
        "ലണ്ടൻ"
      ],
      "answer": "2002",
      "difficulty": "medium"
    },
    {
      "id": "io_042",
      "question": "WTO ആസ്ഥാനം ഏത്?",
      "options": [
        "ജനീവ",
        "റോം",
        "പാരീസ്",
        "ന്യൂയോർക്ക്"
      ],
      "answer": "ജനീവ",
      "difficulty": "medium"
    },
    {
      "id": "io_043",
      "question": "WHO സ്ഥാപിതമായ വർഷം ഏത്?",
      "options": [
        "1950",
        "1960",
        "1948",
        "1945"
      ],
      "answer": "1948",
      "difficulty": "medium"
    },
    {
      "id": "io_044",
      "question": "ILOയുടെ ആസ്ഥാനം എവിടെയാണ്?",
      "options": [
        "സാമ്പത്തിക സഹകരണവും വികസനവും",
        "ജിനീവ",
        "ബ്രിട്ടീഷ് പാരമ്പര്യ രാജ്യങ്ങളുടെ കൂട്ടായ്മ",
        "1961"
      ],
      "answer": "ജിനീവ",
      "difficulty": "medium"
    },
    {
      "id": "io_045",
      "question": "United Nations ആസ്ഥാനം ഏത്?",
      "options": [
        "ന്യൂയോർക്ക്",
        "റോം",
        "ജനീവ",
        "പാരീസ്"
      ],
      "answer": "ന്യൂയോർക്ക്",
      "difficulty": "medium"
    },
    {
      "id": "io_046",
      "question": "Commonwealthയുടെ ആസ്ഥാനം എവിടെയാണ്?",
      "options": [
        "ലണ്ടൻ",
        "ഷാങ്ഹായ്",
        "2015",
        "അവസരസൗകര്യ ധനസഹായം"
      ],
      "answer": "ലണ്ടൻ",
      "difficulty": "medium"
    },
    {
      "id": "io_047",
      "question": "EU സ്ഥാപിതമായത് ഏത് വർഷത്തിലാണ്?",
      "options": [
        "1894",
        "ലോസാൻ",
        "1993",
        "ഒളിമ്പിക് പ്രസ്ഥാന നിയന്ത്രണം"
      ],
      "answer": "1993",
      "difficulty": "medium"
    },
    {
      "id": "io_048",
      "question": "UNEP ആസ്ഥാനം?",
      "options": [
        "ജനീവ",
        "ന്യൂയോർക്ക്",
        "നൈറോബി",
        "പാരീസ്"
      ],
      "answer": "നൈറോബി",
      "difficulty": "hard"
    },
    {
      "id": "io_049",
      "question": "IAEA ആസ്ഥാനം ഏത്?",
      "options": [
        "ജനീവ",
        "വിയന്ന",
        "ന്യൂയോർക്ക്",
        "പാരീസ്"
      ],
      "answer": "വിയന്ന",
      "difficulty": "medium"
    },
    {
      "id": "io_050",
      "question": "UN പൊതുസഭാ അധ്യക്ഷൻ തിരഞ്ഞെടുക്കുന്ന കാലാവധി?",
      "options": [
        "പത്ത് വർഷം",
        "ഒരു വർഷം",
        "ജീവിതകാലം",
        "ഓരോ അഞ്ച് വർഷത്തിലും"
      ],
      "answer": "ഒരു വർഷം",
      "difficulty": "hard"
    },
    {
      "id": "io_051",
      "question": "BRICSയുടെ ആസ്ഥാനം എവിടെയാണ്?",
      "options": [
        "ഭക്ഷ്യവും കൃഷിയും",
        "റോം",
        "ബഹുരാജ്യ വേദി",
        "കുട്ടികളുടെ ക്ഷേമം"
      ],
      "answer": "ബഹുരാജ്യ വേദി",
      "difficulty": "medium"
    },
    {
      "id": "io_052",
      "question": "ഐക്യരാഷ്ട്ര സംഘടനയുടെ ആസ്ഥാനം എവിടെയാണ്?",
      "options": [
        "ന്യൂയോർക്ക്",
        "ജനീവ",
        "പാരിസ്",
        "ലണ്ടൻ"
      ],
      "answer": "ന്യൂയോർക്ക്",
      "difficulty": "easy"
    },
    {
      "id": "io_053",
      "question": "UNDP ആസ്ഥാനം?",
      "options": [
        "പാരീസ്",
        "ന്യൂയോർക്ക്",
        "റോം",
        "ജനീവ"
      ],
      "answer": "ന്യൂയോർക്ക്",
      "difficulty": "hard"
    },
    {
      "id": "io_054",
      "question": "ന്യൂ ഡെവലപ്മെന്റ് ബാങ്ക് ആസ്ഥാനം?",
      "options": [
        "ഷാങ്ഹായ്",
        "ഡൽഹി",
        "മോസ്കോ",
        "ബ്രസീലിയ"
      ],
      "answer": "ഷാങ്ഹായ്",
      "difficulty": "hard"
    },
    {
      "id": "io_055",
      "question": "ILO സ്ഥാപിതമായത് ഏത് വർഷത്തിലാണ്?",
      "options": [
        "ഹേഗ്",
        "1919",
        "1975",
        "വ്യവസായിക ജനാധിപത്യ രാജ്യങ്ങൾ"
      ],
      "answer": "1919",
      "difficulty": "medium"
    },
    {
      "id": "io_056",
      "question": "UNESCO ആസ്ഥാനം ഏത്?",
      "options": [
        "ജനീവ",
        "വിയന്ന",
        "ന്യൂയോർക്ക്",
        "പാരീസ്"
      ],
      "answer": "പാരീസ്",
      "difficulty": "medium"
    },
    {
      "id": "io_057",
      "question": "World Bankയുടെ ആസ്ഥാനം എവിടെയാണ്?",
      "options": [
        "സിംഗപ്പൂർ സെക്രട്ടറിയറ്റ്",
        "BRICS വികസന ബാങ്ക്",
        "1989",
        "വാഷിങ്ടൺ ഡി.സി."
      ],
      "answer": "വാഷിങ്ടൺ ഡി.സി.",
      "difficulty": "medium"
    },
    {
      "id": "io_058",
      "question": "World Health Organization regional office for South-East Asia in?",
      "options": [
        "ജനീവ",
        "Manila",
        "ന്യൂഡൽഹി",
        "കെയ്റോ"
      ],
      "answer": "ന്യൂഡൽഹി",
      "difficulty": "hard"
    },
    {
      "id": "io_059",
      "question": "IMF ആസ്ഥാനം ഏത്?",
      "options": [
        "ലണ്ടൻ",
        "Washington D.C.",
        "ന്യൂയോർക്ക്",
        "പാരീസ്"
      ],
      "answer": "Washington D.C.",
      "difficulty": "medium"
    },
    {
      "id": "io_060",
      "question": "EU സ്ഥാപിതമായ വർഷം ഏത്?",
      "options": [
        "1993",
        "2010",
        "2000",
        "1950"
      ],
      "answer": "1993",
      "difficulty": "medium"
    },
    {
      "id": "io_061",
      "question": "United Nations സ്ഥാപിതമായ വർഷം ഏത്?",
      "options": [
        "1950",
        "1946",
        "1945",
        "1944"
      ],
      "answer": "1945",
      "difficulty": "medium"
    },
    {
      "id": "io_062",
      "question": "ASEANയുടെ ആസ്ഥാനം എവിടെയാണ്?",
      "options": [
        "1971",
        "ജക്കാർത്ത",
        "പരിസ്ഥിതി",
        "മാനവാവകാശം"
      ],
      "answer": "ജക്കാർത്ത",
      "difficulty": "medium"
    },
    {
      "id": "io_063",
      "question": "WTO സ്ഥാപിതമായത് ഏത് വർഷത്തിലാണ്?",
      "options": [
        "യൂറോപ്യൻ രാഷ്ട്രീയ-സാമ്പത്തിക കൂട്ടായ്മ",
        "1993",
        "വിയന്ന",
        "1995"
      ],
      "answer": "1995",
      "difficulty": "medium"
    },
    {
      "id": "io_064",
      "question": "OIC ആസ്ഥാനം ഏത്?",
      "options": [
        "ജിദ്ദ",
        "കെയ്റോ",
        "റിയാദ്",
        "ഇസ്താംബുൾ"
      ],
      "answer": "ജിദ്ദ",
      "difficulty": "medium"
    },
    {
      "id": "io_065",
      "question": "G7 സ്ഥാപിതമായ വർഷം ഏത്?",
      "options": [
        "1990",
        "1975",
        "1960",
        "2000"
      ],
      "answer": "1975",
      "difficulty": "medium"
    },
    {
      "id": "io_066",
      "question": "ASEAN ആസ്ഥാനം ഏത്?",
      "options": [
        "Manila",
        "ജക്കാർത്ത",
        "ബാങ്കോക്ക്",
        "സിംഗപ്പൂർ"
      ],
      "answer": "ജക്കാർത്ത",
      "difficulty": "medium"
    },
    {
      "id": "io_067",
      "question": "BRICS സ്ഥാപിതമായത് ഏത് വർഷത്തിലാണ്?",
      "options": [
        "1989",
        "കെയ്റോ",
        "ഏഷ്യ-പസഫിക് സാമ്പത്തിക സഹകരണം",
        "2009"
      ],
      "answer": "2009",
      "difficulty": "medium"
    },
    {
      "id": "io_068",
      "question": "SAARC സ്ഥാപിതമായത് ഏത് വർഷത്തിലാണ്?",
      "options": [
        "1985",
        "1971",
        "അന്തർദേശീയ മെഡിക്കൽ സഹായം",
        "മാനവാവകാശം"
      ],
      "answer": "1985",
      "difficulty": "medium"
    },
    {
      "id": "io_069",
      "question": "World Bank ആസ്ഥാനം ഏത്?",
      "options": [
        "റോം",
        "Washington D.C.",
        "ജനീവ",
        "പാരീസ്"
      ],
      "answer": "Washington D.C.",
      "difficulty": "medium"
    },
    {
      "id": "io_070",
      "question": "വേൾഡ് ട്രേഡ് ഓർഗനൈസേഷൻ പകരംവെച്ചത്?",
      "options": [
        "UNESCO",
        "NATO",
        "GATT",
        "WHO"
      ],
      "answer": "GATT",
      "difficulty": "hard"
    },
    {
      "id": "io_071",
      "question": "UNയുടെ ആസ്ഥാനം എവിടെയാണ്?",
      "options": [
        "സിംഗപ്പൂർ സെക്രട്ടറിയറ്റ്",
        "BRICS വികസന ബാങ്ക്",
        "1989",
        "ന്യൂയോർക്ക്"
      ],
      "answer": "ന്യൂയോർക്ക്",
      "difficulty": "medium"
    },
    {
      "id": "io_072",
      "question": "WHO സ്ഥാപിതമായത് ഏത് വർഷത്തിലാണ്?",
      "options": [
        "മോണ്ടെവിഡിയോ",
        "1991",
        "യൂറോപ്പിലെ സുരക്ഷ സഹകരണം",
        "1948"
      ],
      "answer": "1948",
      "difficulty": "medium"
    },
    {
      "id": "io_073",
      "question": "UNICEF ആസ്ഥാനം ഏത്?",
      "options": [
        "ജനീവ",
        "പാരീസ്",
        "റോം",
        "ന്യൂയോർക്ക്"
      ],
      "answer": "ന്യൂയോർക്ക്",
      "difficulty": "medium"
    },
    {
      "id": "io_074",
      "question": "Commonwealth ആസ്ഥാനം ഏത്?",
      "options": [
        "ജനീവ",
        "ന്യൂയോർക്ക്",
        "പാരീസ്",
        "ലണ്ടൻ"
      ],
      "answer": "ലണ്ടൻ",
      "difficulty": "medium"
    },
    {
      "id": "io_075",
      "question": "WHO ആസ്ഥാനം ഏത്?",
      "options": [
        "പാരീസ്",
        "ജനീവ",
        "റോം",
        "ന്യൂയോർക്ക്"
      ],
      "answer": "ജനീവ",
      "difficulty": "medium"
    },
    {
      "id": "io_076",
      "question": "African Unionയുടെ ആസ്ഥാനം എവിടെയാണ്?",
      "options": [
        "ബ്രസ്സൽസ്",
        "1985",
        "അഡിസ് അബാബ",
        "ദക്ഷിണേഷ്യൻ പ്രാദേശിക സഹകരണം"
      ],
      "answer": "അഡിസ് അബാബ",
      "difficulty": "medium"
    },
    {
      "id": "io_077",
      "question": "BRICS സ്ഥാപിതമായ വർഷം ഏത്?",
      "options": [
        "2000",
        "2015",
        "2020",
        "2009"
      ],
      "answer": "2009",
      "difficulty": "medium"
    },
    {
      "id": "io_078",
      "question": "International Labour Organization Nobel Peace Prize year?",
      "options": [
        "1980",
        "1945",
        "2000",
        "1969"
      ],
      "answer": "1969",
      "difficulty": "hard"
    },
    {
      "id": "io_079",
      "question": "OPEC സ്ഥാപിതമായ വർഷം ഏത്?",
      "options": [
        "1980",
        "1950",
        "1960",
        "1970"
      ],
      "answer": "1960",
      "difficulty": "medium"
    },
    {
      "id": "io_080",
      "question": "OIC സ്ഥാപിതമായ വർഷം ഏത്?",
      "options": [
        "1969",
        "1980",
        "2000",
        "1950"
      ],
      "answer": "1969",
      "difficulty": "medium"
    },
    {
      "id": "io_081",
      "question": "IMFയുടെ ആസ്ഥാനം എവിടെയാണ്?",
      "options": [
        "ആഫ്രിക്കൻ രാജ്യങ്ങളുടെ കൂട്ടായ്മ",
        "വാഷിങ്ടൺ ഡി.സി.",
        "2002",
        "ലണ്ടൻ"
      ],
      "answer": "വാഷിങ്ടൺ ഡി.സി.",
      "difficulty": "medium"
    },
    {
      "id": "io_082",
      "question": "അന്താരാഷ്ട്ര അണുവിദ്യു ഏജൻസി നിരീക്ഷിക്കുന്നത്?",
      "options": [
        "സമാധാനപരമായ അണുവിദ്യു ഉപയോഗം",
        "ബഹിരാകാശം മാത്രം",
        "ആയുധങ്ങൾ മാത്രം",
        "Only medical"
      ],
      "answer": "സമാധാനപരമായ അണുവിദ്യു ഉപയോഗം",
      "difficulty": "medium"
    },
    {
      "id": "io_083",
      "question": "OPECയുടെ ആസ്ഥാനം എവിടെയാണ്?",
      "options": [
        "1991",
        "ദക്ഷിണ അമേരിക്കൻ വിപണി കൂട്ടായ്മ",
        "ജോർജ്ടൗൺ",
        "വിയന്ന"
      ],
      "answer": "വിയന്ന",
      "difficulty": "medium"
    },
    {
      "id": "io_084",
      "question": "FAO ആസ്ഥാനം ഏത്?",
      "options": [
        "റോം",
        "ന്യൂയോർക്ക്",
        "പാരീസ്",
        "ജനീവ"
      ],
      "answer": "റോം",
      "difficulty": "medium"
    },
    {
      "id": "io_085",
      "question": "NATO ആസ്ഥാനം ഏത്?",
      "options": [
        "Washington",
        "പാരീസ്",
        "ലണ്ടൻ",
        "Brussels"
      ],
      "answer": "Brussels",
      "difficulty": "medium"
    },
    {
      "id": "io_086",
      "question": "ASEAN സ്ഥാപിതമായ വർഷം ഏത്?",
      "options": [
        "1970",
        "1967",
        "1980",
        "1950"
      ],
      "answer": "1967",
      "difficulty": "medium"
    },
    {
      "id": "io_087",
      "question": "African Union ആസ്ഥാനം ഏത്?",
      "options": [
        "കെയ്റോ",
        "നൈറോബി",
        "അഡിസ് അബാബ",
        "ലാഗോസ്"
      ],
      "answer": "അഡിസ് അബാബ",
      "difficulty": "medium"
    },
    {
      "id": "io_088",
      "question": "WTO സ്ഥാപിതമായ വർഷം ഏത്?",
      "options": [
        "2000",
        "1980",
        "1995",
        "1945"
      ],
      "answer": "1995",
      "difficulty": "medium"
    },
    {
      "id": "io_089",
      "question": "African Union സ്ഥാപിതമായ വർഷം ഏത്?",
      "options": [
        "1990",
        "2020",
        "2010",
        "2002"
      ],
      "answer": "2002",
      "difficulty": "medium"
    },
    {
      "id": "io_090",
      "question": "SAARC സ്ഥാപിതമായ വർഷം ഏത്?",
      "options": [
        "2000",
        "1975",
        "1990",
        "1985"
      ],
      "answer": "1985",
      "difficulty": "medium"
    },
    {
      "id": "io_091",
      "question": "UNESCO സ്ഥാപിതമായ വർഷം ഏത്?",
      "options": [
        "1950",
        "1945",
        "1960",
        "1944"
      ],
      "answer": "1945",
      "difficulty": "medium"
    },
    {
      "id": "io_092",
      "question": "UNHCR ആസ്ഥാനം ഏത്?",
      "options": [
        "ന്യൂയോർക്ക്",
        "ജനീവ",
        "റോം",
        "പാരീസ്"
      ],
      "answer": "ജനീവ",
      "difficulty": "medium"
    },
    {
      "id": "io_093",
      "question": "IMF അംഗങ്ങളുടെ എണ്ണം (ഏകദേശം)?",
      "options": [
        "300",
        "190+",
        "50",
        "100"
      ],
      "answer": "190+",
      "difficulty": "hard"
    },
    {
      "id": "io_094",
      "question": "BRICS 2024 വിപുലീകരണ പുതിയ അംഗങ്ങൾ?",
      "options": [
        "Japan, Germany",
        "Egypt, Ethiopia, Iran, UAE, Saudi Arabia",
        "ഓസ്ട്രേലിയ മാത്രം",
        "USA, UK"
      ],
      "answer": "Egypt, Ethiopia, Iran, UAE, Saudi Arabia",
      "difficulty": "hard"
    },
    {
      "id": "io_095",
      "question": "World Bank സ്ഥാപിതമായത് ഏത് വർഷത്തിലാണ്?",
      "options": [
        "പരിസ്ഥിതി",
        "1944",
        "1971",
        "മാനവാവകാശം"
      ],
      "answer": "1944",
      "difficulty": "medium"
    },
    {
      "id": "io_096",
      "question": "ഏഷ്യൻ ഡെവലപ്മെന്റ് ബാങ്ക് ആസ്ഥാനം?",
      "options": [
        "ബാങ്കോക്ക്",
        "Manila",
        "ടോക്കിയോ",
        "ഡൽഹി"
      ],
      "answer": "Manila",
      "difficulty": "hard"
    },
    {
      "id": "io_097",
      "question": "NATO സ്ഥാപിതമായ വർഷം ഏത്?",
      "options": [
        "1949",
        "1960",
        "1945",
        "1970"
      ],
      "answer": "1949",
      "difficulty": "medium"
    },
    {
      "id": "io_098",
      "question": "IMF സ്ഥാപിതമായ വർഷം ഏത്?",
      "options": [
        "1960",
        "1950",
        "1945",
        "1944"
      ],
      "answer": "1944",
      "difficulty": "medium"
    },
    {
      "id": "io_099",
      "question": "Interpol ആസ്ഥാനം ഏത്?",
      "options": [
        "ലയോൺ",
        "ജനീവ",
        "ലണ്ടൻ",
        "പാരീസ്"
      ],
      "answer": "ലയോൺ",
      "difficulty": "medium"
    },
    {
      "id": "io_100",
      "question": "UNICEF സ്ഥാപിതമായ വർഷം ഏത്?",
      "options": [
        "1946",
        "1960",
        "1950",
        "1945"
      ],
      "answer": "1946",
      "difficulty": "medium"
    },
    {
      "id": "io_101",
      "question": "UN സ്ഥാപിതമായത് ഏത് വർഷത്തിലാണ്?",
      "options": [
        "1945",
        "ആഗോള വ്യാപാര നിയമങ്ങൾ",
        "1995",
        "വികസന ധനസഹായം"
      ],
      "answer": "1945",
      "difficulty": "medium"
    },
    {
      "id": "io_102",
      "question": "Interpol സ്ഥാപിതമായ വർഷം ഏത്?",
      "options": [
        "2000",
        "1950",
        "1945",
        "1923"
      ],
      "answer": "1923",
      "difficulty": "medium"
    },
    {
      "id": "io_103",
      "question": "UNESCO സ്ഥാപിതമായത് ഏത് വർഷത്തിലാണ്?",
      "options": [
        "1945",
        "1923",
        "അന്തർദേശീയ പോലീസ് സഹകരണം",
        "ലിയോൺ"
      ],
      "answer": "1945",
      "difficulty": "medium"
    },
    {
      "id": "io_104",
      "question": "OPEC സ്ഥാപിതമായത് ഏത് വർഷത്തിലാണ്?",
      "options": [
        "1923",
        "1960",
        "ലിയോൺ",
        "അന്തർദേശീയ പോലീസ് സഹകരണം"
      ],
      "answer": "1960",
      "difficulty": "medium"
    },
    {
      "id": "io_105",
      "question": "ASEAN അംഗങ്ങളുടെ എണ്ണം?",
      "options": [
        "12",
        "8",
        "15",
        "10"
      ],
      "answer": "10",
      "difficulty": "medium"
    },
    {
      "id": "io_106",
      "question": "G20 സ്ഥാപിതമായ വർഷം ഏത്?",
      "options": [
        "2010",
        "2025",
        "1980",
        "1999"
      ],
      "answer": "1999",
      "difficulty": "medium"
    },
    {
      "id": "io_107",
      "question": "WTOയുടെ ആസ്ഥാനം എവിടെയാണ്?",
      "options": [
        "ജിനീവ",
        "1967",
        "കാഠ്മണ്ഡു",
        "തെക്കുകിഴക്കൻ ഏഷ്യൻ സഹകരണം"
      ],
      "answer": "ജിനീവ",
      "difficulty": "medium"
    },
    {
      "id": "io_108",
      "question": "അന്താരാഷ്ട്ര നീതി ന്യായാധിപസഭ ആസ്ഥാനം?",
      "options": [
        "പാരീസ്",
        "ന്യൂയോർക്ക്",
        "ജനീവ",
        "The Hague"
      ],
      "answer": "The Hague",
      "difficulty": "medium"
    },
    {
      "id": "io_109",
      "question": "Shanghai Cooperation Organisation HQ?",
      "options": [
        "മോസ്കോ",
        "ബീജിംഗ്",
        "ഇസ്ലാമാബാദ്",
        "ഡൽഹി"
      ],
      "answer": "ബീജിംഗ്",
      "difficulty": "hard"
    },
    {
      "id": "io_110",
      "question": "BRICS-ന്റെ യഥാർത്ഥ അംഗങ്ങൾ?",
      "options": [
        "ASEAN members",
        "India മാത്രം",
        "Brazil, Russia, India, China, South Africa",
        "G7 members"
      ],
      "answer": "Brazil, Russia, India, China, South Africa",
      "difficulty": "medium"
    },
    {
      "id": "io_111",
      "question": "Commonwealth സ്ഥാപിതമായ വർഷം ഏത്?",
      "options": [
        "1950",
        "2000",
        "1931",
        "1945"
      ],
      "answer": "1931",
      "difficulty": "medium"
    },
    {
      "id": "io_112",
      "question": "UNICEFയുടെ ആസ്ഥാനം എവിടെയാണ്?",
      "options": [
        "യുദ്ധക്കുറ്റ വിചാരണ",
        "ന്യൂയോർക്ക്",
        "1966",
        "മനില"
      ],
      "answer": "ന്യൂയോർക്ക്",
      "difficulty": "medium"
    }
  ]
}
